src/gate_phase.v
`timescale 1ns/1ps

// Per-half-bridge request interlock.  Dead time is introduced only when the
// currently asserted device and requested device are complementary.
module gate_phase #(
    parameter [5:0] DEAD_TIME_CLKS = 6'd25
) (
    input  wire clk,
    input  wire reset_n,
    input  wire request_high,
    input  wire request_low,
    output reg  gate_high,
    output reg  gate_low
);
    reg [5:0] dead_count;

    always @(posedge clk or negedge reset_n) begin
        if (!reset_n) begin
            gate_high <= 1'b0;
            gate_low <= 1'b0;
            dead_count <= 6'd0;
        end else if (dead_count != 6'd0) begin
            gate_high <= 1'b0;
            gate_low <= 1'b0;
            if (dead_count == 6'd1) begin
                dead_count <= 6'd0;
                // Requests are sampled here, giving latest-request-wins
                // behavior while the phase has both switches off.
                gate_high <= request_high & ~request_low;
                gate_low <= request_low & ~request_high;
            end else begin
                dead_count <= dead_count - 6'd1;
            end
        end else if ((gate_high && request_low) ||
                     (gate_low && request_high)) begin
            gate_high <= 1'b0;
            gate_low <= 1'b0;
            dead_count <= DEAD_TIME_CLKS;
        end else begin
            // A high and low request together is never a legal phase command;
            // fail safe by turning this half bridge off.
            gate_high <= request_high & ~request_low;
            gate_low <= request_low & ~request_high;
        end
    end
endmodule

src/gate_controller.v
`timescale 1ns/1ps

module gate_controller #(
    parameter [5:0] DEAD_TIME_CLKS = 6'd25
) (
    input  wire       clk,
    input  wire       reset_n,
    input  wire       run_enable,
    input  wire       brake_active,
    input  wire       pwm_raw,
    input  wire [5:0] phase_cmd,
    output wire       gh_a,
    output wire       gl_a,
    output wire       gh_b,
    output wire       gl_b,
    output wire       gh_c,
    output wire       gl_c
);
    wire allow_drive;
    wire req_ah, req_al, req_bh, req_bl, req_ch, req_cl;

    assign allow_drive = run_enable && !brake_active;
    // High sides use PWM; selected low sides are continuously asserted.
    assign req_ah = allow_drive && phase_cmd[5] && pwm_raw;
    assign req_al = allow_drive && phase_cmd[4];
    assign req_bh = allow_drive && phase_cmd[3] && pwm_raw;
    assign req_bl = allow_drive && phase_cmd[2];
    assign req_ch = allow_drive && phase_cmd[1] && pwm_raw;
    assign req_cl = allow_drive && phase_cmd[0];

    gate_phase #(.DEAD_TIME_CLKS(DEAD_TIME_CLKS)) phase_a (
        .clk(clk), .reset_n(reset_n), .request_high(req_ah), .request_low(req_al),
        .gate_high(gh_a), .gate_low(gl_a)
    );
    gate_phase #(.DEAD_TIME_CLKS(DEAD_TIME_CLKS)) phase_b (
        .clk(clk), .reset_n(reset_n), .request_high(req_bh), .request_low(req_bl),
        .gate_high(gh_b), .gate_low(gl_b)
    );
    gate_phase #(.DEAD_TIME_CLKS(DEAD_TIME_CLKS)) phase_c (
        .clk(clk), .reset_n(reset_n), .request_high(req_ch), .request_low(req_cl),
        .gate_high(gh_c), .gate_low(gl_c)
    );
endmodule

src/control_fsm.v
`timescale 1ns/1ps

module control_fsm (
    input  wire clk,
    input  wire reset_n,
    input  wire enable,
    input  wire brake,
    input  wire hall_valid,
    input  wire pwm_boundary,
    input  wire fault_condition,
    input  wire fault_latched,
    output reg  run_enable,
    output reg  brake_active,
    output reg  run
);
    localparam [2:0] IDLE    = 3'd0;
    localparam [2:0] STARTUP = 3'd1;
    localparam [2:0] RUN     = 3'd2;
    localparam [2:0] BRAKE   = 3'd3;
    localparam [2:0] FAULT   = 3'd4;

    reg [2:0] state;
    reg [2:0] next_state;

    always @(*) begin
        next_state = state;
        if (fault_condition || fault_latched) begin
            next_state = FAULT;
        end else begin
            case (state)
                IDLE:    if (enable) next_state = STARTUP;
                STARTUP: begin
                    if (!enable) next_state = IDLE;
                    else if (brake) next_state = BRAKE;
                    else if (hall_valid && pwm_boundary) next_state = RUN;
                end
                RUN: begin
                    if (!enable) next_state = IDLE;
                    else if (brake) next_state = BRAKE;
                end
                BRAKE: begin
                    if (!brake) begin
                        if (enable) next_state = STARTUP;
                        else next_state = IDLE;
                    end
                end
                FAULT: next_state = FAULT;
                default: next_state = IDLE;
            endcase
        end
    end

    always @(posedge clk or negedge reset_n) begin
        if (!reset_n)
            state <= IDLE;
        else
            state <= next_state;
    end

    always @(*) begin
        run_enable = (state == RUN) && !fault_latched;
        brake_active = (state == BRAKE);
        run = run_enable;
    end
endmodule

src/fault_manager.v
`timescale 1ns/1ps

module fault_manager (
    input  wire clk,
    input  wire reset_n,
    input  wire oc_fault,
    input  wire uv_fault,
    input  wire ot_fault,
    input  wire hall_fault,
    output wire fault_condition,
    output reg  fault_latched
);
    assign fault_condition = oc_fault | uv_fault | ot_fault | hall_fault;

    always @(posedge clk or negedge reset_n) begin
        if (!reset_n)
            fault_latched <= 1'b0;
        else if (fault_condition)
            fault_latched <= 1'b1;
    end
endmodule

src/hall_commutation.v
`timescale 1ns/1ps

module hall_commutation (
    input  wire       clk,
    input  wire       reset_n,
    input  wire       hall_a,
    input  wire       hall_b,
    input  wire       hall_c,
    input  wire       dir,
    input  wire       pwm_boundary,
    output wire [2:0] hall_sync,
    output wire       hall_valid,
    output reg  [2:0] hall_active,
    output reg        hall_fault,
    output reg  [5:0] phase_cmd
);
    reg [1:0] hall_a_pipe;
    reg [1:0] hall_b_pipe;
    reg [1:0] hall_c_pipe;
    reg [2:0] hall_previous;
    reg [2:0] hall_pending;
    reg       pending_valid;
    reg       bad_hall_observed;
    reg       grace_used;

    assign hall_sync = {hall_a_pipe[1], hall_b_pipe[1], hall_c_pipe[1]};
    assign hall_valid = (hall_sync == 3'b001) || (hall_sync == 3'b101) ||
                        (hall_sync == 3'b100) || (hall_sync == 3'b110) ||
                        (hall_sync == 3'b010) || (hall_sync == 3'b011);

    function valid_transition;
        input [2:0] from_hall;
        input [2:0] to_hall;
        input       direction;
        begin
            valid_transition = 1'b0;
            if (!direction) begin
                case (from_hall)
                    3'b001: valid_transition = (to_hall == 3'b101);
                    3'b101: valid_transition = (to_hall == 3'b100);
                    3'b100: valid_transition = (to_hall == 3'b110);
                    3'b110: valid_transition = (to_hall == 3'b010);
                    3'b010: valid_transition = (to_hall == 3'b011);
                    3'b011: valid_transition = (to_hall == 3'b001);
                    default: valid_transition = 1'b0;
                endcase
            end else begin
                case (from_hall)
                    3'b001: valid_transition = (to_hall == 3'b011);
                    3'b011: valid_transition = (to_hall == 3'b010);
                    3'b010: valid_transition = (to_hall == 3'b110);
                    3'b110: valid_transition = (to_hall == 3'b100);
                    3'b100: valid_transition = (to_hall == 3'b101);
                    3'b101: valid_transition = (to_hall == 3'b001);
                    default: valid_transition = 1'b0;
                endcase
            end
        end
    endfunction

    always @(posedge clk or negedge reset_n) begin
        if (!reset_n) begin
            hall_a_pipe <= 2'b00;
            hall_b_pipe <= 2'b00;
            hall_c_pipe <= 2'b00;
        end else begin
            hall_a_pipe <= {hall_a_pipe[0], hall_a};
            hall_b_pipe <= {hall_b_pipe[0], hall_b};
            hall_c_pipe <= {hall_c_pipe[0], hall_c};
        end
    end

    always @(posedge clk or negedge reset_n) begin
        if (!reset_n) begin
            hall_previous <= 3'b000;
            hall_pending <= 3'b000;
            hall_active <= 3'b000;
            pending_valid <= 1'b0;
            bad_hall_observed <= 1'b0;
            grace_used <= 1'b0;
            hall_fault <= 1'b0;
        end else begin
            // Invalid levels are observed continuously so a stable 000/111
            // state is not hidden merely because it did not transition.
            if (!hall_valid)
                bad_hall_observed <= 1'b1;

            if (hall_sync != hall_previous) begin
                hall_previous <= hall_sync;
                if (hall_valid) begin
                    if ((hall_active == 3'b000) ||
                        valid_transition(hall_active, hall_sync, dir)) begin
                        hall_pending <= hall_sync;
                        pending_valid <= 1'b1;
                    end else begin
                        bad_hall_observed <= 1'b1;
                    end
                end
            end

            if (pwm_boundary) begin
                if (pending_valid) begin
                    hall_active <= hall_pending;
                    pending_valid <= 1'b0;
                end
                if (bad_hall_observed) begin
                    if (grace_used)
                        hall_fault <= 1'b1;
                    else
                        grace_used <= 1'b1;
                end else begin
                    grace_used <= 1'b0;
                end
                bad_hall_observed <= 1'b0;
            end
        end
    end

    always @(*) begin
        case (hall_active)
            3'b001: phase_cmd = 6'b100100; // A+ B-
            3'b101: phase_cmd = 6'b100001; // A+ C-
            3'b100: phase_cmd = 6'b001001; // B+ C-
            3'b110: phase_cmd = 6'b011000; // B+ A-
            3'b010: phase_cmd = 6'b010010; // C+ A-
            3'b011: phase_cmd = 6'b000110; // C+ B-
            default: phase_cmd = 6'b000000;
        endcase
    end
endmodule

src/pwm_generator.v
`timescale 1ns/1ps

module pwm_generator #(
    parameter [10:0] PWM_PERIOD_CLKS = 11'd1250
) (
    input  wire        clk,
    input  wire        reset_n,
    input  wire [9:0]  duty,
    output reg  [10:0] pwm_counter,
    output reg  [9:0]  duty_shadow,
    output reg  [9:0]  duty_active,
    output reg  [10:0] compare_value,
    output wire        pwm_raw,
    output wire        pwm_boundary
);
    // The product is at most 1,278,750.  The extra bits retain explicit
    // arithmetic sizing across conservative Verilog-2001 elaborators.
    localparam [10:0] PWM_LAST_COUNT = PWM_PERIOD_CLKS - 11'd1;
    reg [21:0] duty_product;
    reg [21:0] compare_quotient;

    assign pwm_boundary = (pwm_counter == PWM_LAST_COUNT);
    assign pwm_raw = (pwm_counter < compare_value);

    always @(*) begin
        duty_product = duty_active * PWM_PERIOD_CLKS;
        compare_quotient = duty_product / 1023;
        compare_value = compare_quotient[10:0];
    end

    always @(posedge clk or negedge reset_n) begin
        if (!reset_n) begin
            pwm_counter <= 11'd0;
            duty_shadow <= 10'd0;
            duty_active <= 10'd0;
        end else begin
            duty_shadow <= duty;
            if (pwm_boundary) begin
                pwm_counter <= 11'd0;
                duty_active <= duty_shadow;
            end else begin
                pwm_counter <= pwm_counter + 11'd1;
            end
        end
    end
endmodule

src/reset_sync.v
`timescale 1ns/1ps

// Active-low reset conditioner: assertion is asynchronous; deassertion takes
// two CLK edges.  Downstream sequential logic uses reset_n_sync.
module reset_sync (
    input  wire clk,
    input  wire reset_n,
    output wire reset_n_sync
);
    reg [1:0] release_pipe;

    always @(posedge clk or negedge reset_n) begin
        if (!reset_n)
            release_pipe <= 2'b00;
        else
            release_pipe <= {release_pipe[0], 1'b1};
    end

    assign reset_n_sync = release_pipe[1];
endmodule

src/jagdis_top.v
`timescale 1ns/1ps

module jagdis_top #(
    parameter [10:0] PWM_PERIOD_CLKS = 11'd1250,
    parameter [5:0]  DEAD_TIME_CLKS  = 6'd25
) (
    input  wire       CLK,
    input  wire       RESET_N,
    input  wire       HALL_A,
    input  wire       HALL_B,
    input  wire       HALL_C,
    input  wire [9:0] DUTY,
    input  wire       ENABLE,
    input  wire       DIR,
    input  wire       BRAKE,
    input  wire       OC_FAULT,
    input  wire       UV_FAULT,
    input  wire       OT_FAULT,
    output wire       GH_A,
    output wire       GL_A,
    output wire       GH_B,
    output wire       GL_B,
    output wire       GH_C,
    output wire       GL_C,
    output wire       RUN,
    output wire       FAULT
);
    wire reset_n_sync;
    wire [10:0] pwm_counter;
    wire [9:0] duty_shadow, duty_active;
    wire [10:0] compare_value;
    wire pwm_raw, pwm_boundary;
    wire [2:0] hall_sync;
    wire hall_valid, hall_fault;
    wire [2:0] hall_active;
    wire [5:0] phase_cmd;
    wire run_enable, brake_active, run_internal;
    wire fault_condition, fault_latched;
    wire gh_a_normal, gl_a_normal, gh_b_normal, gl_b_normal, gh_c_normal, gl_c_normal;

    reset_sync reset_conditioner (.clk(CLK), .reset_n(RESET_N), .reset_n_sync(reset_n_sync));

    pwm_generator #(.PWM_PERIOD_CLKS(PWM_PERIOD_CLKS)) pwm (
        .clk(CLK), .reset_n(reset_n_sync), .duty(DUTY), .pwm_counter(pwm_counter),
        .duty_shadow(duty_shadow), .duty_active(duty_active), .compare_value(compare_value),
        .pwm_raw(pwm_raw), .pwm_boundary(pwm_boundary)
    );

    hall_commutation hall (
        .clk(CLK), .reset_n(reset_n_sync), .hall_a(HALL_A), .hall_b(HALL_B), .hall_c(HALL_C),
        .dir(DIR), .pwm_boundary(pwm_boundary), .hall_sync(hall_sync), .hall_valid(hall_valid),
        .hall_active(hall_active), .hall_fault(hall_fault), .phase_cmd(phase_cmd)
    );

    fault_manager faults (
        .clk(CLK), .reset_n(reset_n_sync), .oc_fault(OC_FAULT), .uv_fault(UV_FAULT),
        .ot_fault(OT_FAULT), .hall_fault(hall_fault), .fault_condition(fault_condition),
        .fault_latched(fault_latched)
    );

    control_fsm control (
        .clk(CLK), .reset_n(reset_n_sync), .enable(ENABLE), .brake(BRAKE),
        .hall_valid(hall_valid), .pwm_boundary(pwm_boundary), .fault_condition(fault_condition),
        .fault_latched(fault_latched), .run_enable(run_enable), .brake_active(brake_active),
        .run(run_internal)
    );

    gate_controller #(.DEAD_TIME_CLKS(DEAD_TIME_CLKS)) gates (
        .clk(CLK), .reset_n(reset_n_sync), .run_enable(run_enable), .brake_active(brake_active),
        .pwm_raw(pwm_raw), .phase_cmd(phase_cmd), .gh_a(gh_a_normal), .gl_a(gl_a_normal),
        .gh_b(gh_b_normal), .gl_b(gl_b_normal), .gh_c(gh_c_normal), .gl_c(gl_c_normal)
    );

    // RESET_N and external faults bypass all sequential logic.  hall_fault is
    // synchronous, but after grace it receives the same immediate gate kill.
    assign GH_A = gh_a_normal & RESET_N & ~fault_condition & ~fault_latched;
    assign GL_A = gl_a_normal & RESET_N & ~fault_condition & ~fault_latched;
    assign GH_B = gh_b_normal & RESET_N & ~fault_condition & ~fault_latched;
    assign GL_B = gl_b_normal & RESET_N & ~fault_condition & ~fault_latched;
    assign GH_C = gh_c_normal & RESET_N & ~fault_condition & ~fault_latched;
    assign GL_C = gl_c_normal & RESET_N & ~fault_condition & ~fault_latched;
    assign RUN = run_internal & ~fault_condition;
    assign FAULT = fault_latched;
endmodule

testbench/jagdis_top_smoke_tb.v
`timescale 1ns/1ps

// Small integration smoke test for the frozen V1 start and fault behavior.
module jagdis_top_smoke_tb;
    reg clk = 1'b0;
    reg reset_n = 1'b0;
    reg hall_a = 1'b0;
    reg hall_b = 1'b0;
    reg hall_c = 1'b1; // 001: A+ B-
    reg [9:0] duty = 10'd1023;
    reg enable = 1'b1;
    reg dir = 1'b0;
    reg brake = 1'b0;
    reg oc_fault = 1'b0;
    reg uv_fault = 1'b0;
    reg ot_fault = 1'b0;
    wire gh_a, gl_a, gh_b, gl_b, gh_c, gl_c, run, fault;

    always #10 clk = ~clk;

    jagdis_top dut (
        .CLK(clk), .RESET_N(reset_n), .HALL_A(hall_a), .HALL_B(hall_b), .HALL_C(hall_c),
        .DUTY(duty), .ENABLE(enable), .DIR(dir), .BRAKE(brake),
        .OC_FAULT(oc_fault), .UV_FAULT(uv_fault), .OT_FAULT(ot_fault),
        .GH_A(gh_a), .GL_A(gl_a), .GH_B(gh_b), .GL_B(gl_b), .GH_C(gh_c), .GL_C(gl_c),
        .RUN(run), .FAULT(fault)
    );

    initial begin
        $dumpfile("output/jagdis_top_smoke.vcd");
        $dumpvars(0, jagdis_top_smoke_tb);
        #35 reset_n = 1'b1;
        // Two PWM periods cover reset release, Hall synchronization, shadow
        // transfer, and boundary-aligned startup.
        #51000;
        if (!run || !gh_a || !gl_b || gl_a || gh_b || gl_c || gh_c) begin
            $display("FAIL: expected A+ B- operation after startup");
            $finish;
        end
        oc_fault = 1'b1;
        #1;
        if (gh_a || gl_a || gh_b || gl_b || gh_c || gl_c) begin
            $display("FAIL: external fault did not asynchronously kill gates");
            $finish;
        end
        #30;
        if (!fault || run) begin
            $display("FAIL: fault did not latch and clear RUN");
            $finish;
        end
        $display("PASS: JAGDIS top-level smoke test");
        $finish;
    end
endmodule

output/jagdis_top_smoke.vcd
$date
	Sun Aug 30 22:34:01 2026
$end
$version
	Icarus Verilog
$end
$timescale
	1ps
$end
$scope module jagdis_top_smoke_tb $end
$var wire 1 ! run $end
$var wire 1 " gl_c $end
$var wire 1 # gl_b $end
$var wire 1 $ gl_a $end
$var wire 1 % gh_c $end
$var wire 1 & gh_b $end
$var wire 1 ' gh_a $end
$var wire 1 ( fault $end
$var reg 1 ) brake $end
$var reg 1 * clk $end
$var reg 1 + dir $end
$var reg 10 , duty [9:0] $end
$var reg 1 - enable $end
$var reg 1 . hall_a $end
$var reg 1 / hall_b $end
$var reg 1 0 hall_c $end
$var reg 1 1 oc_fault $end
$var reg 1 2 ot_fault $end
$var reg 1 3 reset_n $end
$var reg 1 4 uv_fault $end
$scope module dut $end
$var wire 1 ) BRAKE $end
$var wire 1 * CLK $end
$var wire 1 + DIR $end
$var wire 10 5 DUTY [9:0] $end
$var wire 1 - ENABLE $end
$var wire 1 ( FAULT $end
$var wire 1 ' GH_A $end
$var wire 1 & GH_B $end
$var wire 1 % GH_C $end
$var wire 1 $ GL_A $end
$var wire 1 # GL_B $end
$var wire 1 " GL_C $end
$var wire 1 . HALL_A $end
$var wire 1 / HALL_B $end
$var wire 1 0 HALL_C $end
$var wire 1 1 OC_FAULT $end
$var wire 1 2 OT_FAULT $end
$var wire 1 3 RESET_N $end
$var wire 1 ! RUN $end
$var wire 1 4 UV_FAULT $end
$var wire 1 6 run_internal $end
$var wire 1 7 run_enable $end
$var wire 1 8 reset_n_sync $end
$var wire 1 9 pwm_raw $end
$var wire 11 : pwm_counter [10:0] $end
$var wire 1 ; pwm_boundary $end
$var wire 6 < phase_cmd [5:0] $end
$var wire 1 = hall_valid $end
$var wire 3 > hall_sync [2:0] $end
$var wire 1 ? hall_fault $end
$var wire 3 @ hall_active [2:0] $end
$var wire 1 A gl_c_normal $end
$var wire 1 B gl_b_normal $end
$var wire 1 C gl_a_normal $end
$var wire 1 D gh_c_normal $end
$var wire 1 E gh_b_normal $end
$var wire 1 F gh_a_normal $end
$var wire 1 G fault_latched $end
$var wire 1 H fault_condition $end
$var wire 10 I duty_shadow [9:0] $end
$var wire 10 J duty_active [9:0] $end
$var wire 11 K compare_value [10:0] $end
$var wire 1 L brake_active $end
$var parameter 6 M DEAD_TIME_CLKS $end
$var parameter 11 N PWM_PERIOD_CLKS $end
$scope module control $end
$var wire 1 ) brake $end
$var wire 1 * clk $end
$var wire 1 - enable $end
$var wire 1 8 reset_n $end
$var wire 1 ; pwm_boundary $end
$var wire 1 = hall_valid $end
$var wire 1 G fault_latched $end
$var wire 1 H fault_condition $end
$var parameter 3 O BRAKE $end
$var parameter 3 P FAULT $end
$var parameter 3 Q IDLE $end
$var parameter 3 R RUN $end
$var parameter 3 S STARTUP $end
$var reg 1 L brake_active $end
$var reg 3 T next_state [2:0] $end
$var reg 1 6 run $end
$var reg 1 7 run_enable $end
$var reg 3 U state [2:0] $end
$upscope $end
$scope module faults $end
$var wire 1 * clk $end
$var wire 1 H fault_condition $end
$var wire 1 1 oc_fault $end
$var wire 1 2 ot_fault $end
$var wire 1 4 uv_fault $end
$var wire 1 8 reset_n $end
$var wire 1 ? hall_fault $end
$var reg 1 G fault_latched $end
$upscope $end
$scope module gates $end
$var wire 1 V allow_drive $end
$var wire 1 L brake_active $end
$var wire 1 * clk $end
$var wire 1 W req_ah $end
$var wire 1 X req_al $end
$var wire 1 Y req_bh $end
$var wire 1 Z req_bl $end
$var wire 1 [ req_ch $end
$var wire 1 \ req_cl $end
$var wire 1 7 run_enable $end
$var wire 1 8 reset_n $end
$var wire 1 9 pwm_raw $end
$var wire 6 ] phase_cmd [5:0] $end
$var wire 1 A gl_c $end
$var wire 1 B gl_b $end
$var wire 1 C gl_a $end
$var wire 1 D gh_c $end
$var wire 1 E gh_b $end
$var wire 1 F gh_a $end
$var parameter 6 ^ DEAD_TIME_CLKS $end
$scope module phase_a $end
$var wire 1 * clk $end
$var wire 1 W request_high $end
$var wire 1 X request_low $end
$var wire 1 8 reset_n $end
$var parameter 6 _ DEAD_TIME_CLKS $end
$var reg 6 ` dead_count [5:0] $end
$var reg 1 F gate_high $end
$var reg 1 C gate_low $end
$upscope $end
$scope module phase_b $end
$var wire 1 * clk $end
$var wire 1 Y request_high $end
$var wire 1 Z request_low $end
$var wire 1 8 reset_n $end
$var parameter 6 a DEAD_TIME_CLKS $end
$var reg 6 b dead_count [5:0] $end
$var reg 1 E gate_high $end
$var reg 1 B gate_low $end
$upscope $end
$scope module phase_c $end
$var wire 1 * clk $end
$var wire 1 [ request_high $end
$var wire 1 \ request_low $end
$var wire 1 8 reset_n $end
$var parameter 6 c DEAD_TIME_CLKS $end
$var reg 6 d dead_count [5:0] $end
$var reg 1 D gate_high $end
$var reg 1 A gate_low $end
$upscope $end
$upscope $end
$scope module hall $end
$var wire 1 * clk $end
$var wire 1 + dir $end
$var wire 1 . hall_a $end
$var wire 1 / hall_b $end
$var wire 1 0 hall_c $end
$var wire 1 = hall_valid $end
$var wire 1 8 reset_n $end
$var wire 1 ; pwm_boundary $end
$var wire 3 e hall_sync [2:0] $end
$var reg 1 f bad_hall_observed $end
$var reg 1 g grace_used $end
$var reg 2 h hall_a_pipe [1:0] $end
$var reg 3 i hall_active [2:0] $end
$var reg 2 j hall_b_pipe [1:0] $end
$var reg 2 k hall_c_pipe [1:0] $end
$var reg 1 ? hall_fault $end
$var reg 3 l hall_pending [2:0] $end
$var reg 3 m hall_previous [2:0] $end
$var reg 1 n pending_valid $end
$var reg 6 o phase_cmd [5:0] $end
$scope function valid_transition $end
$var reg 1 p direction $end
$var reg 3 q from_hall [2:0] $end
$var reg 3 r to_hall [2:0] $end
$upscope $end
$upscope $end
$scope module pwm $end
$var wire 1 * clk $end
$var wire 10 s duty [9:0] $end
$var wire 1 8 reset_n $end
$var wire 1 9 pwm_raw $end
$var wire 1 ; pwm_boundary $end
$var parameter 11 t PWM_LAST_COUNT $end
$var parameter 11 u PWM_PERIOD_CLKS $end
$var reg 22 v compare_quotient [21:0] $end
$var reg 11 w compare_value [10:0] $end
$var reg 10 x duty_active [9:0] $end
$var reg 22 y duty_product [21:0] $end
$var reg 10 z duty_shadow [9:0] $end
$var reg 11 { pwm_counter [10:0] $end
$upscope $end
$scope module reset_conditioner $end
$var wire 1 * clk $end
$var wire 1 3 reset_n $end
$var wire 1 8 reset_n_sync $end
$var reg 2 | release_pipe [1:0] $end
$upscope $end
$upscope $end
$upscope $end
$enddefinitions $end
$comment Show the parameter values. $end
$dumpall
b10011100010 u
b10011100001 t
b11001 c
b11001 a
b11001 _
b11001 ^
b1 S
b10 R
b0 Q
b100 P
b11 O
b10011100010 N
b11001 M
$end
#0
$dumpvars
b0 |
b0 {
b0 z
b0 y
b0 x
b0 w
b0 v
b1111111111 s
bx r
bx q
xp
b0 o
0n
b0 m
b0 l
b0 k
b0 j
b0 i
b0 h
0g
0f
b0 e
b0 d
b0 b
b0 `
b0 ]
0\
0[
0Z
0Y
0X
0W
0V
b0 U
b1 T
0L
b0 K
b0 J
b0 I
0H
0G
0F
0E
0D
0C
0B
0A
b0 @
0?
b0 >
0=
b0 <
0;
b0 :
09
08
07
06
b1111111111 5
04
03
02
01
10
0/
0.
1-
b1111111111 ,
0+
0*
0)
0(
0'
0&
0%
0$
0#
0"
0!
$end
#10000
1*
#20000
0*
#30000
1*
#35000
13
#40000
0*
#50000
b1 |
1*
#60000
0*
#70000
18
b11 |
1*
#80000
0*
#90000
b1 U
1f
b1 k
b1 :
b1 {
b1111111111 I
b1111111111 z
1*
#100000
0*
#110000
1=
b1 >
b1 e
b10 :
b10 {
b11 k
1*
#120000
0*
#130000
1n
b1 l
b1 m
b11 :
b11 {
1*
#140000
0*
#150000
b100 :
b100 {
1*
#160000
0*
#170000
b101 :
b101 {
1*
#180000
0*
#190000
b110 :
b110 {
1*
#200000
0*
#210000
b111 :
b111 {
1*
#220000
0*
#230000
b1000 :
b1000 {
1*
#240000
0*
#250000
b1001 :
b1001 {
1*
#260000
0*
#270000
b1010 :
b1010 {
1*
#280000
0*
#290000
b1011 :
b1011 {
1*
#300000
0*
#310000
b1100 :
b1100 {
1*
#320000
0*
#330000
b1101 :
b1101 {
1*
#340000
0*
#350000
b1110 :
b1110 {
1*
#360000
0*
#370000
b1111 :
b1111 {
1*
#380000
0*
#390000
b10000 :
b10000 {
1*
#400000
0*
#410000
b10001 :
b10001 {
1*
#420000
0*
#430000
b10010 :
b10010 {
1*
#440000
0*
#450000
b10011 :
b10011 {
1*
#460000
0*
#470000
b10100 :
b10100 {
1*
#480000
0*
#490000
b10101 :
b10101 {
1*
#500000
0*
#510000
b10110 :
b10110 {
1*
#520000
0*
#530000
b10111 :
b10111 {
1*
#540000
0*
#550000
b11000 :
b11000 {
1*
#560000
0*
#570000
b11001 :
b11001 {
1*
#580000
0*
#590000
b11010 :
b11010 {
1*
#600000
0*
#610000
b11011 :
b11011 {
1*
#620000
0*
#630000
b11100 :
b11100 {
1*
#640000
0*
#650000
b11101 :
b11101 {
1*
#660000
0*
#670000
b11110 :
b11110 {
1*
#680000
0*
#690000
b11111 :
b11111 {
1*
#700000
0*
#710000
b100000 :
b100000 {
1*
#720000
0*
#730000
b100001 :
b100001 {
1*
#740000
0*
#750000
b100010 :
b100010 {
1*
#760000
0*
#770000
b100011 :
b100011 {
1*
#780000
0*
#790000
b100100 :
b100100 {
1*
#800000
0*
#810000
b100101 :
b100101 {
1*
#820000
0*
#830000
b100110 :
b100110 {
1*
#840000
0*
#850000
b100111 :
b100111 {
1*
#860000
0*
#870000
b101000 :
b101000 {
1*
#880000
0*
#890000
b101001 :
b101001 {
1*
#900000
0*
#910000
b101010 :
b101010 {
1*
#920000
0*
#930000
b101011 :
b101011 {
1*
#940000
0*
#950000
b101100 :
b101100 {
1*
#960000
0*
#970000
b101101 :
b101101 {
1*
#980000
0*
#990000
b101110 :
b101110 {
1*
#1000000
0*
#1010000
b101111 :
b101111 {
1*
#1020000
0*
#1030000
b110000 :
b110000 {
1*
#1040000
0*
#1050000
b110001 :
b110001 {
1*
#1060000
0*
#1070000
b110010 :
b110010 {
1*
#1080000
0*
#1090000
b110011 :
b110011 {
1*
#1100000
0*
#1110000
b110100 :
b110100 {
1*
#1120000
0*
#1130000
b110101 :
b110101 {
1*
#1140000
0*
#1150000
b110110 :
b110110 {
1*
#1160000
0*
#1170000
b110111 :
b110111 {
1*
#1180000
0*
#1190000
b111000 :
b111000 {
1*
#1200000
0*
#1210000
b111001 :
b111001 {
1*
#1220000
0*
#1230000
b111010 :
b111010 {
1*
#1240000
0*
#1250000
b111011 :
b111011 {
1*
#1260000
0*
#1270000
b111100 :
b111100 {
1*
#1280000
0*
#1290000
b111101 :
b111101 {
1*
#1300000
0*
#1310000
b111110 :
b111110 {
1*
#1320000
0*
#1330000
b111111 :
b111111 {
1*
#1340000
0*
#1350000
b1000000 :
b1000000 {
1*
#1360000
0*
#1370000
b1000001 :
b1000001 {
1*
#1380000
0*
#1390000
b1000010 :
b1000010 {
1*
#1400000
0*
#1410000
b1000011 :
b1000011 {
1*
#1420000
0*
#1430000
b1000100 :
b1000100 {
1*
#1440000
0*
#1450000
b1000101 :
b1000101 {
1*
#1460000
0*
#1470000
b1000110 :
b1000110 {
1*
#1480000
0*
#1490000
b1000111 :
b1000111 {
1*
#1500000
0*
#1510000
b1001000 :
b1001000 {
1*
#1520000
0*
#1530000
b1001001 :
b1001001 {
1*
#1540000
0*
#1550000
b1001010 :
b1001010 {
1*
#1560000
0*
#1570000
b1001011 :
b1001011 {
1*
#1580000
0*
#1590000
b1001100 :
b1001100 {
1*
#1600000
0*
#1610000
b1001101 :
b1001101 {
1*
#1620000
0*
#1630000
b1001110 :
b1001110 {
1*
#1640000
0*
#1650000
b1001111 :
b1001111 {
1*
#1660000
0*
#1670000
b1010000 :
b1010000 {
1*
#1680000
0*
#1690000
b1010001 :
b1010001 {
1*
#1700000
0*
#1710000
b1010010 :
b1010010 {
1*
#1720000
0*
#1730000
b1010011 :
b1010011 {
1*
#1740000
0*
#1750000
b1010100 :
b1010100 {
1*
#1760000
0*
#1770000
b1010101 :
b1010101 {
1*
#1780000
0*
#1790000
b1010110 :
b1010110 {
1*
#1800000
0*
#1810000
b1010111 :
b1010111 {
1*
#1820000
0*
#1830000
b1011000 :
b1011000 {
1*
#1840000
0*
#1850000
b1011001 :
b1011001 {
1*
#1860000
0*
#1870000
b1011010 :
b1011010 {
1*
#1880000
0*
#1890000
b1011011 :
b1011011 {
1*
#1900000
0*
#1910000
b1011100 :
b1011100 {
1*
#1920000
0*
#1930000
b1011101 :
b1011101 {
1*
#1940000
0*
#1950000
b1011110 :
b1011110 {
1*
#1960000
0*
#1970000
b1011111 :
b1011111 {
1*
#1980000
0*
#1990000
b1100000 :
b1100000 {
1*
#2000000
0*
#2010000
b1100001 :
b1100001 {
1*
#2020000
0*
#2030000
b1100010 :
b1100010 {
1*
#2040000
0*
#2050000
b1100011 :
b1100011 {
1*
#2060000
0*
#2070000
b1100100 :
b1100100 {
1*
#2080000
0*
#2090000
b1100101 :
b1100101 {
1*
#2100000
0*
#2110000
b1100110 :
b1100110 {
1*
#2120000
0*
#2130000
b1100111 :
b1100111 {
1*
#2140000
0*
#2150000
b1101000 :
b1101000 {
1*
#2160000
0*
#2170000
b1101001 :
b1101001 {
1*
#2180000
0*
#2190000
b1101010 :
b1101010 {
1*
#2200000
0*
#2210000
b1101011 :
b1101011 {
1*
#2220000
0*
#2230000
b1101100 :
b1101100 {
1*
#2240000
0*
#2250000
b1101101 :
b1101101 {
1*
#2260000
0*
#2270000
b1101110 :
b1101110 {
1*
#2280000
0*
#2290000
b1101111 :
b1101111 {
1*
#2300000
0*
#2310000
b1110000 :
b1110000 {
1*
#2320000
0*
#2330000
b1110001 :
b1110001 {
1*
#2340000
0*
#2350000
b1110010 :
b1110010 {
1*
#2360000
0*
#2370000
b1110011 :
b1110011 {
1*
#2380000
0*
#2390000
b1110100 :
b1110100 {
1*
#2400000
0*
#2410000
b1110101 :
b1110101 {
1*
#2420000
0*
#2430000
b1110110 :
b1110110 {
1*
#2440000
0*
