src/control_fsm.v
`timescale 1ns/1ps

module control_fsm (
    input  wire clk,
    input  wire reset_n,
    input  wire enable,
    input  wire brake,
    input  wire hall_valid,
    input  wire pwm_boundary,
    input  wire fault_condition,
    input  wire fault_latched,
    output reg  run_enable,
    output reg  brake_active,
    output reg  run
);
    localparam [2:0] IDLE    = 3'd0;
    localparam [2:0] STARTUP = 3'd1;
    localparam [2:0] RUN     = 3'd2;
    localparam [2:0] BRAKE   = 3'd3;
    localparam [2:0] FAULT   = 3'd4;

    reg [2:0] state;
    reg [2:0] next_state;

    always @(*) begin
        next_state = state;
        if (fault_condition || fault_latched) begin
            next_state = FAULT;
        end else begin
            case (state)
                IDLE:    if (enable) next_state = STARTUP;
                STARTUP: begin
                    if (!enable) next_state = IDLE;
                    else if (brake) next_state = BRAKE;
                    else if (hall_valid && pwm_boundary) next_state = RUN;
                end
                RUN: begin
                    if (!enable) next_state = IDLE;
                    else if (brake) next_state = BRAKE;
                end
                BRAKE: begin
                    if (!brake) begin
                        if (enable) next_state = STARTUP;
                        else next_state = IDLE;
                    end
                end
                FAULT: next_state = FAULT;
                default: next_state = IDLE;
            endcase
        end
    end

    always @(posedge clk or negedge reset_n) begin
        if (!reset_n)
            state <= IDLE;
        else
            state <= next_state;
    end

    always @(*) begin
        run_enable = (state == RUN) && !fault_latched;
        brake_active = (state == BRAKE);
        run = run_enable;
    end
endmodule

testbench/control_fsm_tb.v
`timescale 1ns/1ps

module control_fsm_tb;

    reg clk;
    reg reset_n;

    reg enable;
    reg brake;
    reg hall_valid;
    reg pwm_boundary;
    reg fault_condition;
    reg fault_latched;

    wire run_enable;
    wire brake_active;
    wire run;

    integer errors;


    control_fsm dut (
        .clk           (clk),
        .reset_n       (reset_n),
        .enable        (enable),
        .brake         (brake),
        .hall_valid    (hall_valid),
        .pwm_boundary  (pwm_boundary),
        .fault_condition(fault_condition),
        .fault_latched (fault_latched),
        .run_enable    (run_enable),
        .brake_active  (brake_active),
        .run           (run)
    );


    always #10 clk = ~clk;


    task fail;
        input [8*100-1:0] message;
        begin
            errors = errors + 1;
            $display("FAIL: %0s", message);
        end
    endtask


    task clear_inputs;
        begin
            enable         = 1'b0;
            brake          = 1'b0;
            hall_valid     = 1'b0;
            pwm_boundary   = 1'b0;
            fault_condition = 1'b0;
            fault_latched  = 1'b0;
        end
    endtask


    task reset_dut;
        begin
            clear_inputs;

            reset_n = 1'b0;

            #1;

            if (dut.state !== 3'd0)
                fail("reset must place FSM in IDLE");

            if (run_enable !== 1'b0)
                fail("run_enable must be low during reset");

            if (brake_active !== 1'b0)
                fail("brake_active must be low during reset");

            if (run !== 1'b0)
                fail("run must be low during reset");

            repeat (3)
                @(posedge clk);

            reset_n = 1'b1;

            repeat (2) begin
                @(posedge clk);
                #1;
            end
        end
    endtask


    task clock_once;
        begin
            @(posedge clk);
            #1;
        end
    endtask


    initial begin

        clk = 1'b0;
        reset_n = 1'b0;

        enable          = 1'b0;
        brake           = 1'b0;
        hall_valid      = 1'b0;
        pwm_boundary    = 1'b0;
        fault_condition = 1'b0;
        fault_latched   = 1'b0;

        errors = 0;

        $dumpfile("output/simulation_artifacts/control_fsm_tb.vcd");
        $dumpvars(0, control_fsm_tb);


        // ============================================================
        // TEST 1: RESET / IDLE
        // ============================================================

        $display("");
        $display("TEST 1: Reset and IDLE");

        reset_dut;

        if (dut.state !== 3'd0)
            fail("FSM must start in IDLE");

        if (run_enable || brake_active || run)
            fail("all outputs must be inactive in IDLE");


        // ============================================================
        // TEST 2: IDLE -> STARTUP
        // ============================================================

        $display("");
        $display("TEST 2: IDLE to STARTUP");

        enable = 1'b1;

        clock_once;

        if (dut.state !== 3'd1)
            fail("ENABLE must move FSM from IDLE to STARTUP");

        if (run_enable)
            fail("STARTUP must not assert run_enable");

        if (run)
            fail("STARTUP must not assert run");

        if (brake_active)
            fail("STARTUP must not assert brake_active");


        // ============================================================
        // TEST 3: STARTUP WAIT FOR HALL + PWM BOUNDARY
        // ============================================================

        $display("");
        $display("TEST 3: STARTUP qualification");

        hall_valid   = 1'b1;
        pwm_boundary = 1'b0;

        clock_once;

        if (dut.state !== 3'd1)
            fail("STARTUP must wait when PWM boundary is absent");

        if (run)
            fail("RUN must not assert before PWM boundary");


        pwm_boundary = 1'b1;

        clock_once;

        if (dut.state !== 3'd2)
            fail("valid Hall plus PWM boundary must enter RUN");

        if (!run_enable)
            fail("RUN must assert run_enable");

        if (!run)
            fail("RUN output must assert in RUN state");

        if (brake_active)
            fail("brake_active must be low in RUN");

        pwm_boundary = 1'b0;


        // ============================================================
        // TEST 4: RUN HOLD
        // ============================================================

        $display("");
        $display("TEST 4: RUN hold");

        clock_once;

        if (dut.state !== 3'd2)
            fail("RUN must remain active while enable is asserted");

        if (!run_enable || !run)
            fail("RUN outputs must remain asserted");


        // ============================================================
        // TEST 5: ENABLE RELEASE -> IDLE
        // ============================================================

        $display("");
        $display("TEST 5: RUN to IDLE");

        enable = 1'b0;

        clock_once;

        if (dut.state !== 3'd0)
            fail("clearing ENABLE must return RUN to IDLE");

        if (run_enable)
            fail("run_enable must clear after leaving RUN");

        if (run)
            fail("run must clear after leaving RUN");


        // ============================================================
        // TEST 6: STARTUP CANCELLED BY ENABLE
        // ============================================================

        $display("");
        $display("TEST 6: STARTUP cancellation");

        reset_dut;

        enable = 1'b1;

        clock_once;

        if (dut.state !== 3'd1)
            fail("ENABLE must enter STARTUP");

        enable = 1'b0;

        clock_once;

        if (dut.state !== 3'd0)
            fail("clearing ENABLE during STARTUP must return to IDLE");


        // ============================================================
        // TEST 7: STARTUP -> BRAKE
        // ============================================================

        $display("");
        $display("TEST 7: STARTUP to BRAKE");

        reset_dut;

        enable = 1'b1;

        clock_once;

        brake = 1'b1;

        clock_once;

        if (dut.state !== 3'd3)
            fail("BRAKE must move STARTUP to BRAKE");

        if (!brake_active)
            fail("BRAKE state must assert brake_active");

        if (run_enable)
            fail("BRAKE state must clear run_enable");

        if (run)
            fail("BRAKE state must clear run");


        // ============================================================
        // TEST 8: BRAKE RELEASE WITH ENABLE
        // ============================================================

        $display("");
        $display("TEST 8: BRAKE release to STARTUP");

        brake = 1'b0;
        enable = 1'b1;

        clock_once;

        if (dut.state !== 3'd1)
            fail("releasing BRAKE with ENABLE must return to STARTUP");

        if (brake_active)
            fail("brake_active must clear after leaving BRAKE");

        if (run)
            fail("STARTUP must not assert run immediately");


        // ============================================================
        // TEST 9: BRAKE RELEASE WITHOUT ENABLE
        // ============================================================

        $display("");
        $display("TEST 9: BRAKE release to IDLE");

        reset_dut;

        enable = 1'b1;

        clock_once;

        brake = 1'b1;

        clock_once;

        if (dut.state !== 3'd3)
            fail("failed to enter BRAKE");

        enable = 1'b0;
        brake  = 1'b0;

        clock_once;

        if (dut.state !== 3'd0)
            fail("releasing BRAKE without ENABLE must enter IDLE");


        // ============================================================
        // TEST 10: FAULT CONDITION
        // ============================================================

        $display("");
        $display("TEST 10: Immediate FAULT transition");

        reset_dut;

        enable = 1'b1;

        clock_once;

        hall_valid   = 1'b1;
        pwm_boundary = 1'b1;

        clock_once;

        if (dut.state !== 3'd2)
            fail("failed to establish RUN before fault test");

        pwm_boundary = 1'b0;

        fault_condition = 1'b1;

        clock_once;

        if (dut.state !== 3'd4)
            fail("fault_condition must move FSM to FAULT");

        if (run_enable)
            fail("run_enable must clear in FAULT");

        if (run)
            fail("run must clear in FAULT");

        if (brake_active)
            fail("FAULT must not assert brake_active");


        // ============================================================
        // TEST 11: FAULT LATCHED
        // ============================================================

        $display("");
        $display("TEST 11: Latched fault forces FAULT");

        reset_dut;

        enable = 1'b1;

        clock_once;

        fault_latched = 1'b1;

        clock_once;

        if (dut.state !== 3'd4)
            fail("fault_latched must force FSM to FAULT");

        if (run_enable || run)
            fail("latched fault must prevent RUN");


        // ============================================================
        // TEST 12: FAULT IS STICKY
        // ============================================================

        $display("");
        $display("TEST 12: FAULT state is sticky");

        fault_latched   = 1'b0;
        fault_condition = 1'b0;
        enable          = 1'b0;

        repeat (5)
            clock_once;

        if (dut.state !== 3'd4)
            fail("FAULT state must remain sticky");

        if (run_enable || run)
            fail("FAULT state must keep drive disabled");


        // ============================================================
        // TEST 13: HALL INVALID BLOCKS STARTUP
        // ============================================================

        $display("");
        $display("TEST 13: Invalid Hall blocks STARTUP");

        reset_dut;

        enable = 1'b1;

        clock_once;

        if (dut.state !== 3'd1)
            fail("failed to enter STARTUP");

        hall_valid   = 1'b0;
        pwm_boundary = 1'b1;

        clock_once;

        if (dut.state !== 3'd1)
            fail("invalid Hall must prevent STARTUP from entering RUN");

        if (run)
            fail("invalid Hall must not permit RUN");


        // ============================================================
        // TEST 14: HALL VALID WITHOUT PWM BOUNDARY
        // ============================================================

        $display("");
        $display("TEST 14: Valid Hall without PWM boundary");

        hall_valid   = 1'b1;
        pwm_boundary = 1'b0;

        clock_once;

        if (dut.state !== 3'd1)
            fail("valid Hall alone must not enter RUN");

        if (run)
            fail("RUN must wait for PWM boundary");


        // ============================================================
        // TEST 15: BRAKE HAS PRIORITY OVER STARTUP RUN
        // ============================================================

        $display("");
        $display("TEST 15: Brake priority during STARTUP");

        reset_dut;

        enable       = 1'b1;
        hall_valid   = 1'b1;
        pwm_boundary = 1'b1;
        brake        = 1'b1;

        clock_once;

        if (dut.state !== 3'd1)
            fail("first ENABLE clock must enter STARTUP");

        clock_once;

        if (dut.state !== 3'd3)
            fail("BRAKE must take priority over RUN qualification");

        if (!brake_active)
            fail("BRAKE state must assert brake_active");

        if (run)
            fail("BRAKE must prevent RUN");


        // ============================================================
        // FINAL RESULT
        // ============================================================

        $display("");

        if (errors == 0)
            $display("PASS: control_fsm unit verification");
        else
            $display(
                "FAIL: control_fsm unit verification: %0d checks failed",
                errors
            );

        $finish;

    end

endmodule

output/simulation_artifacts/control_fsm_tb.vcd
$date
	Mon Sep  7 21:39:39 2026
$end
$version
	Icarus Verilog
$end
$timescale
	1ps
$end
$scope module control_fsm_tb $end
$var wire 1 ! run_enable $end
$var wire 1 " run $end
$var wire 1 # brake_active $end
$var reg 1 $ brake $end
$var reg 1 % clk $end
$var reg 1 & enable $end
$var reg 1 ' fault_condition $end
$var reg 1 ( fault_latched $end
$var reg 1 ) hall_valid $end
$var reg 1 * pwm_boundary $end
$var reg 1 + reset_n $end
$var integer 32 , errors [31:0] $end
$scope module dut $end
$var wire 1 $ brake $end
$var wire 1 % clk $end
$var wire 1 & enable $end
$var wire 1 ' fault_condition $end
$var wire 1 ( fault_latched $end
$var wire 1 ) hall_valid $end
$var wire 1 * pwm_boundary $end
$var wire 1 + reset_n $end
$var parameter 3 - BRAKE $end
$var parameter 3 . FAULT $end
$var parameter 3 / IDLE $end
$var parameter 3 0 RUN $end
$var parameter 3 1 STARTUP $end
$var reg 1 # brake_active $end
$var reg 3 2 next_state [2:0] $end
$var reg 1 " run $end
$var reg 1 ! run_enable $end
$var reg 3 3 state [2:0] $end
$upscope $end
$scope task clear_inputs $end
$upscope $end
$scope task clock_once $end
$upscope $end
$scope task fail $end
$var reg 800 4 message [799:0] $end
$upscope $end
$scope task reset_dut $end
$upscope $end
$upscope $end
$enddefinitions $end
$comment Show the parameter values. $end
$dumpall
b1 1
b10 0
b0 /
b100 .
b11 -
$end
#0
$dumpvars
bx 4
b0 3
b0 2
b0 ,
0+
0*
0)
0(
0'
0&
0%
0$
0#
0"
0!
$end
#10000
1%
#20000
0%
#30000
1%
#40000
0%
#50000
1+
1%
#60000
0%
#70000
1%
#80000
0%
#90000
1%
#91000
b1 2
1&
#100000
0%
#110000
b1 3
1%
#111000
1)
#120000
0%
#130000
1%
#131000
b10 2
1*
#140000
0%
#150000
1"
1!
b10 3
1%
#151000
0*
#160000
0%
#170000
1%
#171000
b0 2
0&
#180000
0%
#190000
0"
0!
b0 3
1%
#191000
0+
0)
#200000
0%
#210000
1%
#220000
0%
#230000
1%
#240000
0%
#250000
1+
1%
#260000
0%
#270000
1%
#280000
0%
#290000
1%
#291000
b1 2
1&
#300000
0%
#310000
b1 3
1%
#311000
b0 2
0&
#320000
0%
#330000
b0 3
1%
#331000
0+
#340000
0%
#350000
1%
#360000
0%
#370000
1%
#380000
0%
#390000
1+
1%
#400000
0%
#410000
1%
#420000
0%
#430000
1%
#431000
b1 2
1&
#440000
0%
#450000
b1 3
1%
#451000
b11 2
1$
#460000
0%
#470000
1#
b11 3
1%
#471000
b1 2
0$
#480000
0%
#490000
0#
b1 3
1%
#491000
b0 3
b0 2
0+
0&
#500000
0%
#510000
1%
#520000
0%
#530000
1%
#540000
0%
#550000
1+
1%
#560000
0%
#570000
1%
#580000
0%
#590000
1%
#591000
b1 2
1&
#600000
0%
#610000
b1 3
1%
#611000
b11 2
1$
#620000
0%
#630000
1#
b11 3
1%
#631000
b0 2
0$
0&
#640000
0%
#650000
0#
b0 3
1%
#651000
0+
#660000
0%
#670000
1%
#680000
0%
#690000
1%
#700000
0%
#710000
1+
1%
#720000
0%
#730000
1%
#740000
0%
#750000
1%
#751000
b1 2
1&
#760000
0%
#770000
b1 3
1%
#771000
b10 2
1*
1)
#780000
0%
#790000
1"
1!
b10 3
1%
#791000
b100 2
1'
0*
#800000
0%
#810000
0"
0!
b100 3
1%
#811000
b0 2
b0 3
0+
0'
0)
0&
#820000
0%
#830000
1%
#840000
0%
#850000
1%
#860000
0%
#870000
1+
1%
#880000
0%
#890000
1%
#900000
0%
#910000
1%
#911000
b1 2
1&
#920000
0%
#930000
b1 3
1%
#931000
b100 2
1(
#940000
0%
#950000
b100 3
1%
#951000
0&
0(
#960000
0%
#970000
1%
#980000
0%
#990000
1%
#1000000
0%
#1010000
1%
#1020000
0%
#1030000
1%
#1040000
0%
#1050000
1%
#1051000
b0 2
b0 3
0+
#1060000
0%
#1070000
1%
#1080000
0%
#1090000
1%
#1100000
0%
#1110000
1+
1%
#1120000
0%
#1130000
1%
#1140000
0%
#1150000
1%
#1151000
b1 2
1&
#1160000
0%
#1170000
b1 3
1%
#1171000
1*
#1180000
0%
#1190000
1%
#1191000
0*
1)
#1200000
0%
#1210000
1%
#1211000
b0 3
b0 2
0+
0)
0&
#1220000
0%
#1230000
1%
#1240000
0%
#1250000
1%
#1260000
0%
#1270000
1+
1%
#1280000
0%
#1290000
1%
#1300000
0%
#1310000
1%
#1311000
b1 2
1$
1*
1)
1&
#1320000
0%
#1330000
b11 2
b1 3
1%
#1340000
0%
#1350000
1#
b11 3
1%
