src/fault_manager.v
`timescale 1ns/1ps

module fault_manager (
    input  wire clk,
    input  wire reset_n,
    input  wire oc_fault,
    input  wire uv_fault,
    input  wire ot_fault,
    input  wire hall_fault,
    output wire fault_condition,
    output reg  fault_latched
);
    assign fault_condition = oc_fault | uv_fault | ot_fault | hall_fault;

    always @(posedge clk or negedge reset_n) begin
        if (!reset_n)
            fault_latched <= 1'b0;
        else if (fault_condition)
            fault_latched <= 1'b1;
    end
endmodule

testbench/fault_manager_tb.v
`timescale 1ns/1ps

module fault_manager_tb;

    reg clk;
    reg reset_n;

    reg oc_fault;
    reg uv_fault;
    reg ot_fault;
    reg hall_fault;

    wire fault_condition;
    wire fault_latched;

    integer errors;


    fault_manager dut (
        .clk            (clk),
        .reset_n        (reset_n),
        .oc_fault       (oc_fault),
        .uv_fault       (uv_fault),
        .ot_fault       (ot_fault),
        .hall_fault     (hall_fault),
        .fault_condition(fault_condition),
        .fault_latched  (fault_latched)
    );


    always #10 clk = ~clk;


    task fail;
        input [8*100-1:0] message;
        begin
            errors = errors + 1;
            $display("FAIL: %0s", message);
        end
    endtask


    task clear_fault_inputs;
        begin
            oc_fault   = 1'b0;
            uv_fault   = 1'b0;
            ot_fault   = 1'b0;
            hall_fault = 1'b0;
        end
    endtask


    task reset_dut;
        begin
            clear_fault_inputs;

            reset_n = 1'b0;

            #1;

            if (fault_condition !== 1'b0)
                fail("fault_condition must be zero during reset");

            if (fault_latched !== 1'b0)
                fail("fault_latched must be zero during reset");

            repeat (3)
                @(posedge clk);

            reset_n = 1'b1;

            repeat (2) begin
                @(posedge clk);
                #1;
            end
        end
    endtask


    initial begin

        clk = 1'b0;
        reset_n = 1'b0;

        oc_fault   = 1'b0;
        uv_fault   = 1'b0;
        ot_fault   = 1'b0;
        hall_fault = 1'b0;

        errors = 0;

        $dumpfile("output/simulation_artifacts/fault_manager_tb.vcd");
        $dumpvars(0, fault_manager_tb);


        // ============================================================
        // TEST 1: RESET
        // ============================================================

        $display("");
        $display("TEST 1: Reset");

        reset_dut;

        if (fault_latched !== 1'b0)
            fail("fault_latched must be clear after reset");

        if (fault_condition !== 1'b0)
            fail("fault_condition must be clear with all faults inactive");


        // ============================================================
        // TEST 2: FAULT CONDITION OR LOGIC
        // ============================================================

        $display("");
        $display("TEST 2: Fault condition OR logic");

        reset_dut;


        // OC only
        oc_fault = 1'b1;
        #1;

        if (fault_condition !== 1'b1)
            fail("OC_FAULT must assert fault_condition");

        clear_fault_inputs;


        // UV only
        uv_fault = 1'b1;
        #1;

        if (fault_condition !== 1'b1)
            fail("UV_FAULT must assert fault_condition");

        clear_fault_inputs;


        // OT only
        ot_fault = 1'b1;
        #1;

        if (fault_condition !== 1'b1)
            fail("OT_FAULT must assert fault_condition");

        clear_fault_inputs;


        // Hall only
        hall_fault = 1'b1;
        #1;

        if (fault_condition !== 1'b1)
            fail("HALL_FAULT must assert fault_condition");

        clear_fault_inputs;


        // All faults together
        oc_fault   = 1'b1;
        uv_fault   = 1'b1;
        ot_fault   = 1'b1;
        hall_fault = 1'b1;
        #1;

        if (fault_condition !== 1'b1)
            fail("multiple simultaneous faults must assert fault_condition");

        clear_fault_inputs;

        #1;

        if (fault_condition !== 1'b0)
            fail("fault_condition must clear when all fault inputs clear");


        // ============================================================
        // TEST 3: OC FAULT LATCHING
        // ============================================================

        $display("");
        $display("TEST 3: Over-current fault latching");

        reset_dut;

        oc_fault = 1'b1;

        @(posedge clk);
        #1;

        if (fault_latched !== 1'b1)
            fail("OC_FAULT must latch fault_latched");

        oc_fault = 1'b0;

        #1;

        if (fault_condition !== 1'b0)
            fail("fault_condition must clear after OC_FAULT is removed");

        if (fault_latched !== 1'b1)
            fail("fault_latched must remain set after OC_FAULT clears");


        // ============================================================
        // TEST 4: UV FAULT LATCHING
        // ============================================================

        $display("");
        $display("TEST 4: Under-voltage fault latching");

        reset_dut;

        uv_fault = 1'b1;

        @(posedge clk);
        #1;

        if (fault_latched !== 1'b1)
            fail("UV_FAULT must latch fault_latched");


        // ============================================================
        // TEST 5: OT FAULT LATCHING
        // ============================================================

        $display("");
        $display("TEST 5: Over-temperature fault latching");

        reset_dut;

        ot_fault = 1'b1;

        @(posedge clk);
        #1;

        if (fault_latched !== 1'b1)
            fail("OT_FAULT must latch fault_latched");


        // ============================================================
        // TEST 6: HALL FAULT LATCHING
        // ============================================================

        $display("");
        $display("TEST 6: Hall fault latching");

        reset_dut;

        hall_fault = 1'b1;

        @(posedge clk);
        #1;

        if (fault_latched !== 1'b1)
            fail("HALL_FAULT must latch fault_latched");


        // ============================================================
        // TEST 7: LATCH PERSISTENCE
        // ============================================================

        $display("");
        $display("TEST 7: Fault latch persistence");

        reset_dut;

        oc_fault = 1'b1;

        @(posedge clk);
        #1;

        if (fault_latched !== 1'b1)
            fail("fault did not latch");

        clear_fault_inputs;

        repeat (10) begin
            @(posedge clk);
            #1;

            if (fault_latched !== 1'b1)
                fail("fault_latched must remain set after fault removal");
        end


        // ============================================================
        // TEST 8: RESET CLEARS LATCH
        // ============================================================

        $display("");
        $display("TEST 8: Reset clears fault latch");

        // At this point the latch should already be set.
        if (fault_latched !== 1'b1)
            fail("test setup failed to create latched fault");

        reset_n = 1'b0;

        #1;

        if (fault_latched !== 1'b0)
            fail("reset must immediately clear fault_latched");

        if (fault_condition !== 1'b0)
            fail("fault_condition must remain clear after reset");

        reset_n = 1'b1;

        repeat (2) begin
            @(posedge clk);
            #1;
        end

        if (fault_latched !== 1'b0)
            fail("fault_latched must remain clear after reset release");


        // ============================================================
        // FINAL RESULT
        // ============================================================

        $display("");

        if (errors == 0)
            $display("PASS: fault_manager unit verification");
        else
            $display(
                "FAIL: fault_manager unit verification: %0d checks failed",
                errors
            );

        $finish;

    end

endmodule

output/simulation_artifacts/fault_manager_tb.vcd
$date
	Mon Sep  7 21:42:33 2026
$end
$version
	Icarus Verilog
$end
$timescale
	1ps
$end
$scope module fault_manager_tb $end
$var wire 1 ! fault_latched $end
$var wire 1 " fault_condition $end
$var reg 1 # clk $end
$var reg 1 $ hall_fault $end
$var reg 1 % oc_fault $end
$var reg 1 & ot_fault $end
$var reg 1 ' reset_n $end
$var reg 1 ( uv_fault $end
$var integer 32 ) errors [31:0] $end
$scope module dut $end
$var wire 1 # clk $end
$var wire 1 " fault_condition $end
$var wire 1 $ hall_fault $end
$var wire 1 % oc_fault $end
$var wire 1 & ot_fault $end
$var wire 1 ' reset_n $end
$var wire 1 ( uv_fault $end
$var reg 1 ! fault_latched $end
$upscope $end
$scope task clear_fault_inputs $end
$upscope $end
$scope task fail $end
$var reg 800 * message [799:0] $end
$upscope $end
$scope task reset_dut $end
$upscope $end
$upscope $end
$enddefinitions $end
$comment Show the parameter values. $end
$dumpall
$end
#0
$dumpvars
bx *
b0 )
0(
0'
0&
0%
0$
0#
0"
0!
$end
#10000
1#
#20000
0#
#30000
1#
#40000
0#
#50000
1'
1#
#60000
0#
#70000
1#
#80000
0#
#90000
1#
#91000
0'
#100000
0#
#110000
1#
#120000
0#
#130000
1#
#140000
0#
#150000
1'
1#
#160000
0#
#170000
1#
#180000
0#
#190000
1#
#191000
1"
1%
#192000
1(
0%
#193000
1&
0(
#194000
1$
0&
#195000
1&
1(
1%
1$
#196000
0"
0$
0&
0(
0%
#197000
0'
#200000
0#
#210000
1#
#220000
0#
#230000
1#
#240000
0#
#250000
1'
1#
#260000
0#
#270000
1#
#280000
0#
#290000
1#
#291000
1"
1%
#300000
0#
#310000
1!
1#
#311000
0"
0%
#312000
0!
0'
#320000
0#
#330000
1#
#340000
0#
#350000
1#
#360000
0#
#370000
1'
1#
#380000
0#
#390000
1#
#400000
0#
#410000
1#
#411000
1"
1(
#420000
0#
#430000
1!
1#
#431000
0!
0"
0'
0(
#440000
0#
#450000
1#
#460000
0#
#470000
1#
#480000
0#
#490000
1'
1#
#500000
0#
#510000
1#
#520000
0#
#530000
1#
#531000
1"
1&
#540000
0#
#550000
1!
1#
#551000
0!
0"
0'
0&
#560000
0#
#570000
1#
#580000
0#
#590000
1#
#600000
0#
#610000
1'
1#
#620000
0#
#630000
1#
#640000
0#
#650000
1#
#651000
1"
1$
#660000
0#
#670000
1!
1#
#671000
0!
0"
0'
0$
#680000
0#
#690000
1#
#700000
0#
#710000
1#
#720000
0#
#730000
1'
1#
#740000
0#
#750000
1#
#760000
0#
#770000
1#
#771000
1"
1%
#780000
0#
#790000
1!
1#
#791000
0"
0%
#800000
0#
#810000
1#
#820000
0#
#830000
1#
#840000
0#
#850000
1#
#860000
0#
#870000
1#
#880000
0#
#890000
1#
#900000
0#
#910000
1#
#920000
0#
#930000
1#
#940000
0#
#950000
1#
#960000
0#
#970000
1#
#980000
0#
#990000
1#
#991000
0!
0'
#992000
1'
