src/gate_phase.v
`timescale 1ns/1ps

// Per-half-bridge request interlock.  Dead time is introduced only when the
// currently asserted device and requested device are complementary.
module gate_phase #(
    parameter [5:0] DEAD_TIME_CLKS = 6'd25
) (
    input  wire clk,
    input  wire reset_n,
    input  wire request_high,
    input  wire request_low,
    output reg  gate_high,
    output reg  gate_low
);
    reg [5:0] dead_count;

    always @(posedge clk or negedge reset_n) begin
        if (!reset_n) begin
            gate_high <= 1'b0;
            gate_low <= 1'b0;
            dead_count <= 6'd0;
        end else if (dead_count != 6'd0) begin
            gate_high <= 1'b0;
            gate_low <= 1'b0;
            if (dead_count == 6'd1) begin
                dead_count <= 6'd0;
                // Requests are sampled here, giving latest-request-wins
                // behavior while the phase has both switches off.
                gate_high <= request_high & ~request_low;
                gate_low <= request_low & ~request_high;
            end else begin
                dead_count <= dead_count - 6'd1;
            end
        end else if ((gate_high && request_low) ||
                     (gate_low && request_high)) begin
            gate_high <= 1'b0;
            gate_low <= 1'b0;
            dead_count <= DEAD_TIME_CLKS;
        end else begin
            // A high and low request together is never a legal phase command;
            // fail safe by turning this half bridge off.
            gate_high <= request_high & ~request_low;
            gate_low <= request_low & ~request_high;
        end
    end
endmodule

src/gate_controller.v
`timescale 1ns/1ps

module gate_controller #(
    parameter [5:0] DEAD_TIME_CLKS = 6'd25
) (
    input  wire       clk,
    input  wire       reset_n,
    input  wire       run_enable,
    input  wire       brake_active,
    input  wire       pwm_raw,
    input  wire [5:0] phase_cmd,
    output wire       gh_a,
    output wire       gl_a,
    output wire       gh_b,
    output wire       gl_b,
    output wire       gh_c,
    output wire       gl_c
);
    wire allow_drive;
    wire req_ah, req_al, req_bh, req_bl, req_ch, req_cl;

    assign allow_drive = run_enable && !brake_active;
    // High sides use PWM; selected low sides are continuously asserted.
    assign req_ah = allow_drive && phase_cmd[5] && pwm_raw;
    assign req_al = allow_drive && phase_cmd[4];
    assign req_bh = allow_drive && phase_cmd[3] && pwm_raw;
    assign req_bl = allow_drive && phase_cmd[2];
    assign req_ch = allow_drive && phase_cmd[1] && pwm_raw;
    assign req_cl = allow_drive && phase_cmd[0];

    gate_phase #(.DEAD_TIME_CLKS(DEAD_TIME_CLKS)) phase_a (
        .clk(clk), .reset_n(reset_n), .request_high(req_ah), .request_low(req_al),
        .gate_high(gh_a), .gate_low(gl_a)
    );
    gate_phase #(.DEAD_TIME_CLKS(DEAD_TIME_CLKS)) phase_b (
        .clk(clk), .reset_n(reset_n), .request_high(req_bh), .request_low(req_bl),
        .gate_high(gh_b), .gate_low(gl_b)
    );
    gate_phase #(.DEAD_TIME_CLKS(DEAD_TIME_CLKS)) phase_c (
        .clk(clk), .reset_n(reset_n), .request_high(req_ch), .request_low(req_cl),
        .gate_high(gh_c), .gate_low(gl_c)
    );
endmodule

testbench/gate_controller_tb.v
`timescale 1ns/1ps

module gate_controller_tb;

    reg clk;
    reg reset_n;
    reg run_enable;
    reg brake_active;
    reg pwm_raw;
    reg [5:0] phase_cmd;

    wire gh_a, gl_a;
    wire gh_b, gl_b;
    wire gh_c, gl_c;

    integer errors;
    integer i;

    gate_controller #(
        .DEAD_TIME_CLKS(6'd25)
    ) dut (
        .clk          (clk),
        .reset_n      (reset_n),
        .run_enable   (run_enable),
        .brake_active (brake_active),
        .pwm_raw      (pwm_raw),
        .phase_cmd    (phase_cmd),
        .gh_a         (gh_a),
        .gl_a         (gl_a),
        .gh_b         (gh_b),
        .gl_b         (gl_b),
        .gh_c         (gh_c),
        .gl_c         (gl_c)
    );

    always #10 clk = ~clk;


    task fail;
        input [8*100-1:0] message;
        begin
            errors = errors + 1;
            $display("FAIL: %0s", message);
        end
    endtask


    task reset_dut;
        begin
            run_enable   = 1'b0;
            brake_active = 1'b0;
            pwm_raw      = 1'b0;
            phase_cmd    = 6'b000000;

            reset_n = 1'b0;
            #1;

            if ({gh_a,gl_a,gh_b,gl_b,gh_c,gl_c} !== 6'b000000)
                fail("reset must force all gates low");

            repeat (3)
                @(posedge clk);

            reset_n = 1'b1;

            repeat (2) begin
                @(posedge clk);
                #1;
            end
        end
    endtask


    task check_all_off;
        input [8*100-1:0] message;
        begin
            if ({gh_a,gl_a,gh_b,gl_b,gh_c,gl_c} !== 6'b000000)
                fail(message);
        end
    endtask


    task check_no_shoot_through;
        begin
            if (gh_a && gl_a)
                fail("phase A high and low gates must never overlap");

            if (gh_b && gl_b)
                fail("phase B high and low gates must never overlap");

            if (gh_c && gl_c)
                fail("phase C high and low gates must never overlap");
        end
    endtask


    initial begin

        clk = 1'b0;
        reset_n = 1'b0;

        run_enable   = 1'b0;
        brake_active = 1'b0;
        pwm_raw      = 1'b0;
        phase_cmd    = 6'b000000;

        errors = 0;

        $dumpfile("output/simulation_artifacts/gate_controller_tb.vcd");
        $dumpvars(0, gate_controller_tb);


        // ============================================================
        // TEST 1: RESET
        // ============================================================

        $display("");
        $display("TEST 1: Reset");

        reset_dut;

        check_all_off("reset must leave all gates off");


        // ============================================================
        // TEST 2: DISABLED CONTROLLER
        // ============================================================

        $display("");
        $display("TEST 2: Run disabled");

        phase_cmd  = 6'b100100;
        pwm_raw    = 1'b1;
        run_enable = 1'b0;

        @(posedge clk);
        #1;

        check_all_off("run_enable=0 must disable all gates");


        // ============================================================
        // TEST 3: FORWARD PHASE COMMANDS
        // ============================================================

        $display("");
        $display("TEST 3: Six-step phase command mapping");

        run_enable = 1'b1;
        pwm_raw    = 1'b1;


        // 001 = A+ B-
        phase_cmd = 6'b100100;

        @(posedge clk);
        #1;

        if ({gh_a,gl_a,gh_b,gl_b,gh_c,gl_c} !== 6'b100100)
            fail("001 phase command must produce A+ B-");

        check_no_shoot_through;


        // 101 = A+ C-
        phase_cmd = 6'b100001;

        // Allow A transition and C activation.
        repeat (26) begin
            @(posedge clk);
            #1;
            check_no_shoot_through;
        end

        if ({gh_a,gl_a,gh_b,gl_b,gh_c,gl_c} !== 6'b100001)
            fail("101 phase command must produce A+ C-");

        check_no_shoot_through;


        // 100 = B+ C-
        phase_cmd = 6'b001001;

        repeat (26) begin
            @(posedge clk);
            #1;
            check_no_shoot_through;
        end

        if ({gh_a,gl_a,gh_b,gl_b,gh_c,gl_c} !== 6'b001001)
            fail("100 phase command must produce B+ C-");


        // 110 = B+ A-
        phase_cmd = 6'b011000;

        repeat (26) begin
            @(posedge clk);
            #1;
            check_no_shoot_through;
        end

        if ({gh_a,gl_a,gh_b,gl_b,gh_c,gl_c} !== 6'b011000)
            fail("110 phase command must produce B+ A-");


        // 010 = C+ A-
        phase_cmd = 6'b010010;

        repeat (26) begin
            @(posedge clk);
            #1;
            check_no_shoot_through;
        end

        if ({gh_a,gl_a,gh_b,gl_b,gh_c,gl_c} !== 6'b010010)
            fail("010 phase command must produce C+ A-");


        // 011 = C+ B-
        phase_cmd = 6'b000110;

        repeat (26) begin
            @(posedge clk);
            #1;
            check_no_shoot_through;
        end

        if ({gh_a,gl_a,gh_b,gl_b,gh_c,gl_c} !== 6'b000110)
            fail("011 phase command must produce C+ B-");


        // ============================================================
        // TEST 4: PWM HIGH-SIDE CONTROL
        // ============================================================

        $display("");
        $display("TEST 4: PWM high-side control");

        phase_cmd = 6'b100100;
        pwm_raw   = 1'b0;

        repeat (26) begin
            @(posedge clk);
            #1;
        end

        if (gh_a !== 1'b0)
            fail("PWM low must turn selected high side off");

        if (gl_b !== 1'b1)
            fail("selected low side must remain on when PWM is low");

        if (gl_a !== 1'b0 || gh_b !== 1'b0 ||
            gh_c !== 1'b0 || gl_c !== 1'b0)
            fail("unselected gates must remain off");


        pwm_raw = 1'b1;

        @(posedge clk);
        #1;

        if (gh_a !== 1'b1)
            fail("PWM high must enable selected high side");

        if (gl_b !== 1'b1)
            fail("selected low side must remain on with PWM high");

        check_no_shoot_through;


        // ============================================================
        // TEST 5: BRAKE
        // ============================================================

        $display("");
        $display("TEST 5: Brake");

        brake_active = 1'b1;

        repeat (26) begin
            @(posedge clk);
            #1;
        end

        check_all_off("brake_active must turn all gates off");

        brake_active = 1'b0;


        // ============================================================
        // TEST 6: ZERO PHASE COMMAND
        // ============================================================

        $display("");
        $display("TEST 6: Zero phase command");

        phase_cmd = 6'b000000;
        pwm_raw   = 1'b1;

        repeat (26) begin
            @(posedge clk);
            #1;
        end

        check_all_off("zero phase command must turn all gates off");


        // ============================================================
        // TEST 7: INVALID SIMULTANEOUS PHASE REQUEST
        // ============================================================

        $display("");
        $display("TEST 7: Invalid phase command");

        // Request both devices in phase A.
        phase_cmd = 6'b110000;

        repeat (2) begin
            @(posedge clk);
            #1;
        end

        if (gh_a !== 1'b0 || gl_a !== 1'b0)
            fail("simultaneous A high and low request must fail safe");

        check_no_shoot_through;


        // ============================================================
        // TEST 8: COMMUTATION DEAD TIME
        // ============================================================

        $display("");
        $display("TEST 8: Commutation dead time");

        reset_dut;

        run_enable = 1'b1;
        pwm_raw    = 1'b1;

        // Start A+ B-.
        phase_cmd = 6'b100100;

        @(posedge clk);
        #1;

        if (gh_a !== 1'b1 || gl_b !== 1'b1)
            fail("failed to establish A+ B- before dead-time test");

        // Change to B+ C-.
        // A high must turn off before B high becomes active.
        phase_cmd = 6'b001001;

        @(posedge clk);
        #1;

        if (gh_a || gl_a)
            fail("phase A must be off when leaving A+ state");

        // All phases should remain shoot-through safe.
        check_no_shoot_through;

        // Verify dead interval.
        for (i = 0; i < 24; i = i + 1) begin
            @(posedge clk);
            #1;
            check_no_shoot_through;
        end

        // After the dead time the requested B+/C- state should appear.
        @(posedge clk);
        #1;

        if ({gh_a,gl_a,gh_b,gl_b,gh_c,gl_c} !== 6'b001001)
            fail("new commutation state did not appear after dead time");

        check_no_shoot_through;


        // ============================================================
        // TEST 9: RUN DISABLE
        // ============================================================

        $display("");
        $display("TEST 9: Run disable");

        run_enable = 1'b0;

        repeat (26) begin
            @(posedge clk);
            #1;
        end

        check_all_off("disabling run_enable must turn all gates off");


        // ============================================================
        // FINAL RESULT
        // ============================================================

        $display("");

        if (errors == 0)
            $display("PASS: gate_controller unit verification");
        else
            $display(
                "FAIL: gate_controller unit verification: %0d checks failed",
                errors
            );

        $finish;
    end

endmodule

output/simulation_artifacts/gate_controller_tb.vcd
$date
	Mon Sep  7 21:44:08 2026
$end
$version
	Icarus Verilog
$end
$timescale
	1ps
$end
$scope module gate_controller_tb $end
$var wire 1 ! gl_c $end
$var wire 1 " gl_b $end
$var wire 1 # gl_a $end
$var wire 1 $ gh_c $end
$var wire 1 % gh_b $end
$var wire 1 & gh_a $end
$var reg 1 ' brake_active $end
$var reg 1 ( clk $end
$var reg 6 ) phase_cmd [5:0] $end
$var reg 1 * pwm_raw $end
$var reg 1 + reset_n $end
$var reg 1 , run_enable $end
$var integer 32 - errors [31:0] $end
$var integer 32 . i [31:0] $end
$scope module dut $end
$var wire 1 / allow_drive $end
$var wire 1 ' brake_active $end
$var wire 1 ( clk $end
$var wire 6 0 phase_cmd [5:0] $end
$var wire 1 * pwm_raw $end
$var wire 1 1 req_ah $end
$var wire 1 2 req_al $end
$var wire 1 3 req_bh $end
$var wire 1 4 req_bl $end
$var wire 1 5 req_ch $end
$var wire 1 6 req_cl $end
$var wire 1 + reset_n $end
$var wire 1 , run_enable $end
$var wire 1 ! gl_c $end
$var wire 1 " gl_b $end
$var wire 1 # gl_a $end
$var wire 1 $ gh_c $end
$var wire 1 % gh_b $end
$var wire 1 & gh_a $end
$var parameter 6 7 DEAD_TIME_CLKS $end
$scope module phase_a $end
$var wire 1 ( clk $end
$var wire 1 1 request_high $end
$var wire 1 2 request_low $end
$var wire 1 + reset_n $end
$var parameter 6 8 DEAD_TIME_CLKS $end
$var reg 6 9 dead_count [5:0] $end
$var reg 1 & gate_high $end
$var reg 1 # gate_low $end
$upscope $end
$scope module phase_b $end
$var wire 1 ( clk $end
$var wire 1 3 request_high $end
$var wire 1 4 request_low $end
$var wire 1 + reset_n $end
$var parameter 6 : DEAD_TIME_CLKS $end
$var reg 6 ; dead_count [5:0] $end
$var reg 1 % gate_high $end
$var reg 1 " gate_low $end
$upscope $end
$scope module phase_c $end
$var wire 1 ( clk $end
$var wire 1 5 request_high $end
$var wire 1 6 request_low $end
$var wire 1 + reset_n $end
$var parameter 6 < DEAD_TIME_CLKS $end
$var reg 6 = dead_count [5:0] $end
$var reg 1 $ gate_high $end
$var reg 1 ! gate_low $end
$upscope $end
$upscope $end
$scope task check_all_off $end
$var reg 800 > message [799:0] $end
$upscope $end
$scope task check_no_shoot_through $end
$upscope $end
$scope task fail $end
$var reg 800 ? message [799:0] $end
$upscope $end
$scope task reset_dut $end
$upscope $end
$upscope $end
$enddefinitions $end
$comment Show the parameter values. $end
$dumpall
b11001 <
b11001 :
b11001 8
b11001 7
$end
#0
$dumpvars
bx ?
bx >
b0 =
b0 ;
b0 9
06
05
04
03
02
01
b0 0
0/
bx .
b0 -
0,
0+
0*
b0 )
0(
0'
0&
0%
0$
0#
0"
0!
$end
#10000
1(
#20000
0(
#30000
1(
#40000
0(
#50000
1+
1(
#60000
0(
#70000
1(
#80000
0(
#90000
1(
#91000
1*
b100100 )
b100100 0
b11100100110010101110011011001010111010000100000011011010111010101110011011101000010000001101100011001010110000101110110011001010010000001100001011011000110110000100000011001110110000101110100011001010111001100100000011011110110011001100110 >
#100000
0(
#110000
1(
#111000
11
14
1/
1,
b111001001110101011011100101111101100101011011100110000101100010011011000110010100111101001100000010000001101101011101010111001101110100001000000110010001101001011100110110000101100010011011000110010100100000011000010110110001101100001000000110011101100001011101000110010101110011 >
#120000
0(
#130000
1"
1&
1(
#131000
04
16
b100001 )
b100001 0
#140000
0(
#150000
0"
1!
1(
#160000
0(
#170000
1(
#180000
0(
#190000
1(
#200000
0(
#210000
1(
#220000
0(
#230000
1(
#240000
0(
#250000
1(
#260000
0(
#270000
1(
#280000
0(
#290000
1(
#300000
0(
#310000
1(
#320000
0(
#330000
1(
#340000
0(
#350000
1(
#360000
0(
#370000
1(
#380000
0(
#390000
1(
#400000
0(
#410000
1(
#420000
0(
#430000
1(
#440000
0(
#450000
1(
#460000
0(
#470000
1(
#480000
0(
#490000
1(
#500000
0(
#510000
1(
#520000
0(
#530000
1(
#540000
0(
#550000
1(
#560000
0(
#570000
1(
#580000
0(
#590000
1(
#600000
0(
#610000
1(
#620000
0(
#630000
1(
#640000
0(
#650000
1(
#651000
01
13
b1001 )
b1001 0
#660000
0(
#670000
0&
1%
1(
