src/gate_phase.v
`timescale 1ns/1ps

// Per-half-bridge request interlock.  Dead time is introduced only when the
// currently asserted device and requested device are complementary.
module gate_phase #(
    parameter [5:0] DEAD_TIME_CLKS = 6'd25
) (
    input  wire clk,
    input  wire reset_n,
    input  wire request_high,
    input  wire request_low,
    output reg  gate_high,
    output reg  gate_low
);
    reg [5:0] dead_count;

    always @(posedge clk or negedge reset_n) begin
        if (!reset_n) begin
            gate_high <= 1'b0;
            gate_low <= 1'b0;
            dead_count <= 6'd0;
        end else if (dead_count != 6'd0) begin
            gate_high <= 1'b0;
            gate_low <= 1'b0;
            if (dead_count == 6'd1) begin
                dead_count <= 6'd0;
                // Requests are sampled here, giving latest-request-wins
                // behavior while the phase has both switches off.
                gate_high <= request_high & ~request_low;
                gate_low <= request_low & ~request_high;
            end else begin
                dead_count <= dead_count - 6'd1;
            end
        end else if ((gate_high && request_low) ||
                     (gate_low && request_high)) begin
            gate_high <= 1'b0;
            gate_low <= 1'b0;
            dead_count <= DEAD_TIME_CLKS;
        end else begin
            // A high and low request together is never a legal phase command;
            // fail safe by turning this half bridge off.
            gate_high <= request_high & ~request_low;
            gate_low <= request_low & ~request_high;
        end
    end
endmodule

testbench/gate_phase_tb.v
`timescale 1ns/1ps

module gate_phase_tb;

    reg clk;
    reg reset_n;

    reg request_high;
    reg request_low;

    wire gate_high;
    wire gate_low;

    integer errors;
    integer i;

    gate_phase #(
        .DEAD_TIME_CLKS(6'd25)
    ) dut (
        .clk          (clk),
        .reset_n      (reset_n),
        .request_high (request_high),
        .request_low  (request_low),
        .gate_high    (gate_high),
        .gate_low     (gate_low)
    );

    always #10 clk = ~clk;


    task fail;
        input [8*100-1:0] message;
        begin
            errors = errors + 1;
            $display("FAIL: %0s", message);
        end
    endtask


    task reset_dut;
        begin
            request_high = 1'b0;
            request_low  = 1'b0;

            reset_n = 1'b0;
            #1;

            if (gate_high !== 1'b0)
                fail("reset must force gate_high low");

            if (gate_low !== 1'b0)
                fail("reset must force gate_low low");

            repeat (3)
                @(posedge clk);

            reset_n = 1'b1;

            repeat (2) begin
                @(posedge clk);
                #1;
            end
        end
    endtask


    initial begin

        clk = 1'b0;
        reset_n = 1'b0;

        request_high = 1'b0;
        request_low  = 1'b0;

        errors = 0;

        $dumpfile("output/simulation_artifacts/gate_phase_tb.vcd");
        $dumpvars(0, gate_phase_tb);


        // ============================================================
        // TEST 1: RESET
        // ============================================================

        $display("");
        $display("TEST 1: Reset");

        reset_dut;

        if (gate_high !== 1'b0 || gate_low !== 1'b0)
            fail("both gates must be off after reset");


        // ============================================================
        // TEST 2: HIGH-SIDE REQUEST
        // ============================================================

        $display("");
        $display("TEST 2: High-side request");

        request_high = 1'b1;
        request_low  = 1'b0;

        @(posedge clk);
        #1;

        if (gate_high !== 1'b1)
            fail("high-side request must enable gate_high");

        if (gate_low !== 1'b0)
            fail("high-side request must keep gate_low off");


        // ============================================================
        // TEST 3: LOW-SIDE REQUEST WITH DEAD TIME
        // ============================================================

        $display("");
        $display("TEST 3: High-to-low dead time");

        // Request low while high is currently active.
        request_high = 1'b0;
        request_low  = 1'b1;

        @(posedge clk);
        #1;

        // Both must immediately turn off.
        if (gate_high !== 1'b0 || gate_low !== 1'b0)
            fail("high-to-low transition must first turn both gates off");

        // Exactly 24 additional clocks must still remain dead.
        for (i = 0; i < 24; i = i + 1) begin
            @(posedge clk);
            #1;

            if (gate_high !== 1'b0 || gate_low !== 1'b0)
                fail("gate enabled before 25-clock dead time expired");
        end

        // The 25th clock after entering dead time should enable low.
        @(posedge clk);
        #1;

        if (gate_high !== 1'b0 || gate_low !== 1'b1)
            fail("low-side gate did not enable after 25-clock dead time");


        // ============================================================
        // TEST 4: LOW-TO-HIGH DEAD TIME
        // ============================================================

        $display("");
        $display("TEST 4: Low-to-high dead time");

        request_high = 1'b1;
        request_low  = 1'b0;

        @(posedge clk);
        #1;

        if (gate_high !== 1'b0 || gate_low !== 1'b0)
            fail("low-to-high transition must first turn both gates off");

        for (i = 0; i < 24; i = i + 1) begin
            @(posedge clk);
            #1;

            if (gate_high !== 1'b0 || gate_low !== 1'b0)
                fail("gate enabled before 25-clock dead time expired");
        end

        @(posedge clk);
        #1;

        if (gate_high !== 1'b1 || gate_low !== 1'b0)
            fail("high-side gate did not enable after 25-clock dead time");


        // ============================================================
        // TEST 5: BOTH REQUESTS HIGH
        // ============================================================

        $display("");
        $display("TEST 5: Simultaneous high and low request");

        request_high = 1'b1;
        request_low  = 1'b1;

        @(posedge clk);
        #1;

        if (gate_high !== 1'b0 || gate_low !== 1'b0)
            fail("simultaneous high and low request must fail safe");


        // ============================================================
        // TEST 6: BOTH REQUESTS LOW
        // ============================================================

        $display("");
        $display("TEST 6: Both requests off");

        request_high = 1'b0;
        request_low  = 1'b0;

        @(posedge clk);
        #1;

        if (gate_high !== 1'b0 || gate_low !== 1'b0)
            fail("both gates must remain off when both requests are low");


        // ============================================================
        // TEST 7: LATEST REQUEST WINS DURING DEAD TIME
        // ============================================================

        $display("");
        $display("TEST 7: Latest request wins during dead time");

        // Start this test from a clean, known state.
        // TEST 5 intentionally starts a dead-time interval, so simply
        // turning both requests off in TEST 6 does not immediately clear it.
        reset_dut;
        
        // Establish high-side operation.
        request_high = 1'b1;
        request_low  = 1'b0;

        @(posedge clk);
        #1;

        if (gate_high !== 1'b1 || gate_low !== 1'b0)
            fail("failed to establish high-side operation");

        // Start high-to-low transition.
        request_high = 1'b0;
        request_low  = 1'b1;

        @(posedge clk);
        #1;

        if (gate_high !== 1'b0 || gate_low !== 1'b0)
            fail("dead time did not begin");

        // While dead time is active, reverse the request.
        request_high = 1'b1;
        request_low  = 1'b0;

        // Remain in dead time.
        for (i = 0; i < 24; i = i + 1) begin
            @(posedge clk);
            #1;

            if (gate_high !== 1'b0 || gate_low !== 1'b0)
                fail("gate enabled before dead time expired");
        end

        // Latest request should determine the final state.
        @(posedge clk);
        #1;

        if (gate_high !== 1'b1 || gate_low !== 1'b0)
            fail("latest request did not win after dead time");


        // ============================================================
        // TEST 8: RESET DURING DEAD TIME
        // ============================================================

        $display("");
        $display("TEST 8: Reset during dead time");

        // Establish high-side operation.
        request_high = 1'b1;
        request_low  = 1'b0;

        @(posedge clk);
        #1;

        if (gate_high !== 1'b1 || gate_low !== 1'b0)
            fail("failed to establish high-side operation");

        // Start transition into dead time.
        request_high = 1'b0;
        request_low  = 1'b1;

        @(posedge clk);
        #1;

        if (gate_high !== 1'b0 || gate_low !== 1'b0)
            fail("dead time did not begin before reset test");

        // Assert reset asynchronously.
        reset_n = 1'b0;
        #1;

        if (gate_high !== 1'b0 || gate_low !== 1'b0)
            fail("reset during dead time must keep both gates off");

        // Release reset.
        reset_n = 1'b1;

        repeat (2) begin
            @(posedge clk);
            #1;
        end

        if (gate_high !== 1'b0 || gate_low !== 1'b1)
            fail("post-reset low-side request was not handled correctly");


        // ============================================================
        // FINAL RESULT
        // ============================================================

        $display("");

        if (errors == 0)
            $display("PASS: gate_phase unit verification");
        else
            $display(
                "FAIL: gate_phase unit verification: %0d checks failed",
                errors
            );

        $finish;
    end

endmodule

output/simulation_artifacts/gate_phase_tb.vcd
$date
	Mon Sep  7 21:44:51 2026
$end
$version
	Icarus Verilog
$end
$timescale
	1ps
$end
$scope module gate_phase_tb $end
$var wire 1 ! gate_low $end
$var wire 1 " gate_high $end
$var reg 1 # clk $end
$var reg 1 $ request_high $end
$var reg 1 % request_low $end
$var reg 1 & reset_n $end
$var integer 32 ' errors [31:0] $end
$var integer 32 ( i [31:0] $end
$scope module dut $end
$var wire 1 # clk $end
$var wire 1 $ request_high $end
$var wire 1 % request_low $end
$var wire 1 & reset_n $end
$var parameter 6 ) DEAD_TIME_CLKS $end
$var reg 6 * dead_count [5:0] $end
$var reg 1 " gate_high $end
$var reg 1 ! gate_low $end
$upscope $end
$scope task fail $end
$var reg 800 + message [799:0] $end
$upscope $end
$scope task reset_dut $end
$upscope $end
$upscope $end
$enddefinitions $end
$comment Show the parameter values. $end
$dumpall
b11001 )
$end
#0
$dumpvars
bx +
b0 *
bx (
b0 '
0&
0%
0$
0#
0"
0!
$end
#10000
1#
#20000
0#
#30000
1#
#40000
0#
#50000
1&
1#
#60000
0#
#70000
1#
#80000
0#
#90000
1#
#91000
1$
#100000
0#
#110000
1"
1#
#111000
1%
0$
#120000
0#
#130000
b11001 *
0"
1#
#131000
b0 (
#140000
0#
#150000
b11000 *
1#
#151000
b1 (
#160000
0#
#170000
b10111 *
1#
#171000
b10 (
#180000
0#
#190000
b10110 *
1#
#191000
b11 (
#200000
0#
#210000
b10101 *
1#
#211000
b100 (
#220000
0#
#230000
b10100 *
1#
#231000
b101 (
#240000
0#
#250000
b10011 *
1#
#251000
b110 (
#260000
0#
#270000
b10010 *
1#
#271000
b111 (
#280000
0#
#290000
b10001 *
1#
#291000
b1000 (
#300000
0#
#310000
b10000 *
1#
#311000
b1001 (
#320000
0#
#330000
b1111 *
1#
#331000
b1010 (
#340000
0#
#350000
b1110 *
1#
#351000
b1011 (
#360000
0#
#370000
b1101 *
1#
#371000
b1100 (
#380000
0#
#390000
b1100 *
1#
#391000
b1101 (
#400000
0#
#410000
b1011 *
1#
#411000
b1110 (
#420000
0#
#430000
b1010 *
1#
#431000
b1111 (
#440000
0#
#450000
b1001 *
1#
#451000
b10000 (
#460000
0#
#470000
b1000 *
1#
#471000
b10001 (
#480000
0#
#490000
b111 *
1#
#491000
b10010 (
#500000
0#
#510000
b110 *
1#
#511000
b10011 (
#520000
0#
#530000
b101 *
1#
#531000
b10100 (
#540000
0#
#550000
b100 *
1#
#551000
b10101 (
#560000
0#
#570000
b11 *
1#
#571000
b10110 (
#580000
0#
#590000
b10 *
1#
#591000
b10111 (
#600000
0#
#610000
b1 *
1#
#611000
b11000 (
#620000
0#
#630000
1!
b0 *
1#
#631000
0%
1$
#640000
0#
#650000
b11001 *
0!
1#
#651000
b0 (
#660000
0#
#670000
b11000 *
1#
#671000
b1 (
#680000
0#
#690000
b10111 *
1#
#691000
b10 (
#700000
0#
#710000
b10110 *
1#
#711000
b11 (
#720000
0#
#730000
b10101 *
1#
#731000
b100 (
#740000
0#
#750000
b10100 *
1#
#751000
b101 (
#760000
0#
#770000
b10011 *
1#
#771000
b110 (
#780000
0#
#790000
b10010 *
1#
#791000
b111 (
#800000
0#
#810000
b10001 *
1#
#811000
b1000 (
#820000
0#
#830000
b10000 *
1#
#831000
b1001 (
#840000
0#
#850000
b1111 *
1#
#851000
b1010 (
#860000
0#
#870000
b1110 *
1#
#871000
b1011 (
#880000
0#
#890000
b1101 *
1#
#891000
b1100 (
#900000
0#
#910000
b1100 *
1#
#911000
b1101 (
#920000
0#
#930000
b1011 *
1#
#931000
b1110 (
#940000
0#
#950000
b1010 *
1#
#951000
b1111 (
#960000
0#
#970000
b1001 *
1#
#971000
b10000 (
#980000
0#
#990000
b1000 *
1#
#991000
b10001 (
#1000000
0#
#1010000
b111 *
1#
#1011000
b10010 (
#1020000
0#
#1030000
b110 *
1#
#1031000
b10011 (
#1040000
0#
#1050000
b101 *
1#
#1051000
b10100 (
#1060000
0#
#1070000
b100 *
1#
#1071000
b10101 (
#1080000
0#
#1090000
b11 *
1#
#1091000
b10110 (
#1100000
0#
#1110000
b10 *
1#
#1111000
b10111 (
#1120000
0#
#1130000
b1 *
1#
#1131000
b11000 (
#1140000
0#
#1150000
1"
b0 *
1#
#1151000
1%
#1160000
0#
#1170000
b11001 *
0"
1#
#1171000
0%
0$
#1180000
0#
#1190000
b11000 *
1#
#1191000
b0 *
0&
#1200000
0#
#1210000
1#
#1220000
0#
#1230000
1#
#1240000
0#
#1250000
1&
1#
#1260000
0#
#1270000
1#
#1280000
0#
#1290000
1#
#1291000
1$
#1300000
0#
#1310000
1"
1#
#1311000
1%
0$
#1320000
0#
#1330000
b11001 *
0"
1#
#1331000
b0 (
0%
1$
#1340000
0#
#1350000
b11000 *
1#
#1351000
b1 (
#1360000
0#
#1370000
b10111 *
1#
#1371000
b10 (
#1380000
0#
#1390000
b10110 *
1#
#1391000
b11 (
#1400000
0#
#1410000
b10101 *
1#
#1411000
b100 (
#1420000
0#
#1430000
b10100 *
1#
#1431000
b101 (
#1440000
0#
#1450000
b10011 *
1#
#1451000
b110 (
#1460000
0#
#1470000
b10010 *
1#
#1471000
b111 (
#1480000
0#
#1490000
b10001 *
1#
#1491000
b1000 (
#1500000
0#
#1510000
b10000 *
1#
#1511000
b1001 (
#1520000
0#
#1530000
b1111 *
1#
#1531000
b1010 (
#1540000
0#
#1550000
b1110 *
1#
#1551000
b1011 (
#1560000
0#
#1570000
b1101 *
1#
#1571000
b1100 (
#1580000
0#
#1590000
b1100 *
1#
#1591000
b1101 (
#1600000
0#
#1610000
b1011 *
1#
#1611000
b1110 (
#1620000
0#
#1630000
b1010 *
1#
#1631000
b1111 (
#1640000
0#
#1650000
b1001 *
1#
#1651000
b10000 (
#1660000
0#
#1670000
b1000 *
1#
#1671000
b10001 (
#1680000
0#
#1690000
b111 *
1#
#1691000
b10010 (
#1700000
0#
#1710000
b110 *
1#
#1711000
b10011 (
#1720000
0#
#1730000
b101 *
1#
#1731000
b10100 (
#1740000
0#
#1750000
b100 *
1#
#1751000
b10101 (
#1760000
0#
#1770000
b11 *
1#
#1771000
b10110 (
#1780000
0#
#1790000
b10 *
1#
#1791000
b10111 (
#1800000
0#
#1810000
b1 *
1#
#1811000
b11000 (
#1820000
0#
#1830000
1"
b0 *
1#
#1840000
0#
#1850000
1#
#1851000
1%
0$
#1860000
0#
#1870000
b11001 *
0"
1#
#1871000
b0 *
0&
#1872000
1&
#1880000
0#
#1890000
1!
1#
