src/hall_commutation.v
`timescale 1ns/1ps

module hall_commutation (
    input  wire       clk,
    input  wire       reset_n,
    input  wire       hall_a,
    input  wire       hall_b,
    input  wire       hall_c,
    input  wire       dir,
    input  wire       pwm_boundary,
    output wire [2:0] hall_sync,
    output wire       hall_valid,
    output reg  [2:0] hall_active,
    output reg        hall_fault,
    output reg  [5:0] phase_cmd
);

reg [1:0] hall_a_pipe;
reg [1:0] hall_b_pipe;
reg [1:0] hall_c_pipe;

reg [2:0] hall_previous;
reg [2:0] hall_pending;
reg       pending_valid;

reg       bad_hall_observed;
reg       grace_used;

wire [2:0] transition_reference;

assign hall_sync = {
    hall_a_pipe[1],
    hall_b_pipe[1],
    hall_c_pipe[1]
};

assign hall_valid =
       (hall_sync == 3'b001) ||
       (hall_sync == 3'b101) ||
       (hall_sync == 3'b100) ||
       (hall_sync == 3'b110) ||
       (hall_sync == 3'b010) ||
       (hall_sync == 3'b011);

/*
 * If a Hall state is already pending, validate the next Hall state
 * against that pending state. Otherwise validate against the currently
 * active commutation state.
 *
 * This implements the frozen "latest valid Hall state wins" rule.
 */
assign transition_reference =
    pending_valid ? hall_pending : hall_active;


function valid_transition;
    input [2:0] from_hall;
    input [2:0] to_hall;
    input       direction;

    begin
        valid_transition = 1'b0;

        if (!direction) begin
            case (from_hall)
                3'b001: valid_transition = (to_hall == 3'b101);
                3'b101: valid_transition = (to_hall == 3'b100);
                3'b100: valid_transition = (to_hall == 3'b110);
                3'b110: valid_transition = (to_hall == 3'b010);
                3'b010: valid_transition = (to_hall == 3'b011);
                3'b011: valid_transition = (to_hall == 3'b001);
                default: valid_transition = 1'b0;
            endcase
        end else begin
            case (from_hall)
                3'b001: valid_transition = (to_hall == 3'b011);
                3'b011: valid_transition = (to_hall == 3'b010);
                3'b010: valid_transition = (to_hall == 3'b110);
                3'b110: valid_transition = (to_hall == 3'b100);
                3'b100: valid_transition = (to_hall == 3'b101);
                3'b101: valid_transition = (to_hall == 3'b001);
                default: valid_transition = 1'b0;
            endcase
        end
    end
endfunction


/*
 * Hall input synchronizers.
 */
always @(posedge clk or negedge reset_n) begin
    if (!reset_n) begin
        hall_a_pipe <= 2'b00;
        hall_b_pipe <= 2'b00;
        hall_c_pipe <= 2'b00;
    end else begin
        hall_a_pipe <= {hall_a_pipe[0], hall_a};
        hall_b_pipe <= {hall_b_pipe[0], hall_b};
        hall_c_pipe <= {hall_c_pipe[0], hall_c};
    end
end


/*
 * Hall validation, pending-state management, and PWM-boundary activation.
 */
always @(posedge clk or negedge reset_n) begin
    if (!reset_n) begin
        hall_previous      <= 3'b000;
        hall_pending       <= 3'b000;
        hall_active        <= 3'b000;
        pending_valid      <= 1'b0;
        bad_hall_observed  <= 1'b0;
        grace_used         <= 1'b0;
        hall_fault         <= 1'b0;
    end else begin

        /*
         * Any invalid synchronized Hall level is considered bad,
         * even if it remains unchanged.
         */
        if (!hall_valid)
            bad_hall_observed <= 1'b1;

        /*
         * Process a newly observed synchronized Hall state.
         */
        if (hall_sync != hall_previous) begin
            hall_previous <= hall_sync;

            if (hall_valid) begin

                /*
                 * During startup, any valid Hall state may become
                 * the initial pending state.
                 *
                 * During normal operation, validate against the
                 * latest pending state when one exists.
                 */
                if ((hall_active == 3'b000) ||
                    valid_transition(transition_reference,
                                     hall_sync,
                                     dir)) begin

                    hall_pending  <= hall_sync;
                    pending_valid <= 1'b1;

                end else begin
                    bad_hall_observed <= 1'b1;
                end

            end
        end

        /*
         * PWM boundary:
         * commit the latest pending Hall state and process the
         * one-PWM-cycle Hall grace period.
         */
        if (pwm_boundary) begin

            if (pending_valid) begin
                hall_active   <= hall_pending;
                pending_valid <= 1'b0;
            end

            if (!hall_valid) begin
                if (grace_used)
                    hall_fault <= 1'b1;
                else
                    grace_used <= 1'b1;
            end else begin
                grace_used <= 1'b0;
            end

        end
    end
end


/*
 * Hall state → six-step phase command.
 *
 * phase_cmd = {AH, AL, BH, BL, CH, CL}
 */
always @(*) begin
    case (hall_active)
        3'b001: phase_cmd = 6'b100100; // A+ B-
        3'b101: phase_cmd = 6'b100001; // A+ C-
        3'b100: phase_cmd = 6'b001001; // B+ C-
        3'b110: phase_cmd = 6'b011000; // B+ A-
        3'b010: phase_cmd = 6'b010010; // C+ A-
        3'b011: phase_cmd = 6'b000110; // C+ B-
        default: phase_cmd = 6'b000000;
    endcase
end

endmodule

testbench/hall_commutation_tb.v
`timescale 1ns/1ps

module hall_commutation_tb;

    reg clk;
    reg reset_n;

    reg hall_a;
    reg hall_b;
    reg hall_c;

    reg dir;
    reg pwm_boundary;

    wire [2:0] hall_sync;
    wire       hall_valid;
    wire [2:0] hall_active;
    wire       hall_fault;
    wire [5:0] phase_cmd;

    integer errors;
    integer i;

    hall_commutation dut (
        .clk          (clk),
        .reset_n      (reset_n),
        .hall_a       (hall_a),
        .hall_b       (hall_b),
        .hall_c       (hall_c),
        .dir          (dir),
        .pwm_boundary (pwm_boundary),
        .hall_sync    (hall_sync),
        .hall_valid   (hall_valid),
        .hall_active  (hall_active),
        .hall_fault   (hall_fault),
        .phase_cmd    (phase_cmd)
    );

    always #10 clk = ~clk;


    task fail;
        input [8*100-1:0] message;
        begin
            errors = errors + 1;
            $display("FAIL: %0s", message);
        end
    endtask


    task set_hall;
        input [2:0] hall_value;
        begin
            {hall_a, hall_b, hall_c} = hall_value;
        end
    endtask


    task reset_dut;
        begin
            hall_a       = 1'b0;
            hall_b       = 1'b0;
            hall_c       = 1'b0;
            dir          = 1'b0;
            pwm_boundary = 1'b0;

            reset_n = 1'b0;

            #1;

            if (hall_active !== 3'b000)
                fail("reset must clear hall_active");

            if (hall_fault !== 1'b0)
                fail("reset must clear hall_fault");

            if (phase_cmd !== 6'b000000)
                fail("reset must produce zero phase command");

            repeat (3)
                @(posedge clk);

            reset_n = 1'b1;

            repeat (3) begin
                @(posedge clk);
                #1;
            end
        end
    endtask


    task pulse_pwm_boundary;
        begin
            pwm_boundary = 1'b1;
            @(posedge clk);
            #1;
            pwm_boundary = 1'b0;
        end
    endtask

    task wait_for_pending;
        input [2:0] expected_hall;
        begin
            i = 0;

            while ((!dut.pending_valid ||
                    dut.hall_pending !== expected_hall) &&
                (i < 20)) begin
                @(posedge clk);
                #1;
                i = i + 1;
            end

            if (!dut.pending_valid ||
                dut.hall_pending !== expected_hall)
                fail("Hall state did not become pending");
        end
    endtask

    initial begin

        clk          = 1'b0;
        reset_n      = 1'b0;

        hall_a       = 1'b0;
        hall_b       = 1'b0;
        hall_c       = 1'b0;

        dir          = 1'b0;
        pwm_boundary = 1'b0;

        errors = 0;


        $dumpfile("output/simulation_artifacts/hall_commutation_tb.vcd");
        $dumpvars(0, hall_commutation_tb);


        // ============================================================
        // TEST 1: RESET
        // ============================================================

        $display("");
        $display("TEST 1: Reset");

        reset_dut;

        if (hall_active !== 3'b000)
            fail("hall_active incorrect after reset");

        if (hall_fault !== 1'b0)
            fail("hall_fault incorrect after reset");

        if (phase_cmd !== 6'b000000)
            fail("phase_cmd incorrect after reset");


        // ============================================================
        // TEST 2: HALL VALIDITY
        // ============================================================

        $display("");
        $display("TEST 2: Hall validity");

        reset_dut;

        set_hall(3'b001);

        repeat (3) begin
            @(posedge clk);
            #1;
        end

        if (!hall_valid)
            fail("001 should be a valid Hall state");

        set_hall(3'b101);

        repeat (3) begin
            @(posedge clk);
            #1;
        end

        if (!hall_valid)
            fail("101 should be a valid Hall state");

        set_hall(3'b100);

        repeat (3) begin
            @(posedge clk);
            #1;
        end

        if (!hall_valid)
            fail("100 should be a valid Hall state");

        set_hall(3'b110);

        repeat (3) begin
            @(posedge clk);
            #1;
        end

        if (!hall_valid)
            fail("110 should be a valid Hall state");

        set_hall(3'b010);

        repeat (3) begin
            @(posedge clk);
            #1;
        end

        if (!hall_valid)
            fail("010 should be a valid Hall state");

        set_hall(3'b011);

        repeat (3) begin
            @(posedge clk);
            #1;
        end

        if (!hall_valid)
            fail("011 should be a valid Hall state");

        set_hall(3'b111);

        repeat (3) begin
            @(posedge clk);
            #1;
        end

        if (hall_valid)
            fail("111 must be an invalid Hall state");

        set_hall(3'b000);

        repeat (3) begin
            @(posedge clk);
            #1;
        end

        if (hall_valid)
            fail("000 must be an invalid Hall state");


        // ============================================================
        // TEST 3: FORWARD COMMUTATION
        // ============================================================

        $display("");
        $display("TEST 3: Forward Hall transition validation");

        reset_dut;

        dir = 1'b0;


        // Startup Hall = 001.
        // Because hall_active is 000 after reset, any valid Hall state
        // is allowed to establish the initial pending state.

        set_hall(3'b001);
        wait_for_pending(3'b001);

        if (hall_active !== 3'b000)
            fail("Hall active changed before PWM boundary");

        pulse_pwm_boundary;

        if (hall_active !== 3'b001)
            fail("001 was not activated at PWM boundary");


        // 001 -> 101

        set_hall(3'b101);
        wait_for_pending(3'b101);

        if (hall_active !== 3'b001)
            fail("hall_active changed before 001 -> 101 PWM boundary");

        pulse_pwm_boundary;

        if (hall_active !== 3'b101)
            fail("101 was not activated at PWM boundary");


        // 101 -> 100

        set_hall(3'b100);
        wait_for_pending(3'b100);

        if (hall_active !== 3'b101)
            fail("hall_active changed before 101 -> 100 PWM boundary");

        pulse_pwm_boundary;

        if (hall_active !== 3'b100)
            fail("100 was not activated at PWM boundary");


        // 100 -> 110

        set_hall(3'b110);
        wait_for_pending(3'b110);

        if (hall_active !== 3'b100)
            fail("hall_active changed before 100 -> 110 PWM boundary");

        pulse_pwm_boundary;

        if (hall_active !== 3'b110)
            fail("110 was not activated at PWM boundary");


        // 110 -> 010

        set_hall(3'b010);
        wait_for_pending(3'b010);

        if (hall_active !== 3'b110)
            fail("hall_active changed before 110 -> 010 PWM boundary");

        pulse_pwm_boundary;

        if (hall_active !== 3'b010)
            fail("010 was not activated at PWM boundary");


        // 010 -> 011

        set_hall(3'b011);
        wait_for_pending(3'b011);

        if (hall_active !== 3'b010)
            fail("hall_active changed before 010 -> 011 PWM boundary");

        pulse_pwm_boundary;

        if (hall_active !== 3'b011)
            fail("011 was not activated at PWM boundary");


        // 011 -> 001

        set_hall(3'b001);
        wait_for_pending(3'b001);

        if (hall_active !== 3'b011)
            fail("hall_active changed before 011 -> 001 PWM boundary");

        pulse_pwm_boundary;

        if (hall_active !== 3'b001)
            fail("001 wrap transition was not activated at PWM boundary");

        // ============================================================
        // TEST 4: PHASE LOOKUP
        // ============================================================

        $display("");
        $display("TEST 4: Hall-to-phase lookup");

        if (phase_cmd !== 6'b100100)
            fail("Hall 001 must command A+ B-");

        set_hall(3'b101);
        repeat (3) @(posedge clk);
        pulse_pwm_boundary;

        if (phase_cmd !== 6'b100001)
            fail("Hall 101 must command A+ C-");

        set_hall(3'b100);
        repeat (3) @(posedge clk);
        pulse_pwm_boundary;

        if (phase_cmd !== 6'b001001)
            fail("Hall 100 must command B+ C-");

        set_hall(3'b110);
        repeat (3) @(posedge clk);
        pulse_pwm_boundary;

        if (phase_cmd !== 6'b011000)
            fail("Hall 110 must command B+ A-");

        set_hall(3'b010);
        repeat (3) @(posedge clk);
        pulse_pwm_boundary;

        if (phase_cmd !== 6'b010010)
            fail("Hall 010 must command C+ A-");

        set_hall(3'b011);
        repeat (3) @(posedge clk);
        pulse_pwm_boundary;

        if (phase_cmd !== 6'b000110)
            fail("Hall 011 must command C+ B-");


        // ============================================================
        // TEST 5: INVALID TRANSITION REJECTION
        // ============================================================

        $display("");
        $display("TEST 5: Invalid Hall transition rejection");

        reset_dut;

        dir = 1'b0;

        set_hall(3'b001);
        repeat (3) @(posedge clk);
        pulse_pwm_boundary;

        if (hall_active !== 3'b001)
            fail("invalid-transition test failed to establish Hall 001");

        // 001 -> 100 is not a valid forward transition.
        set_hall(3'b100);
        repeat (3) @(posedge clk);

        if (dut.pending_valid)
            fail("invalid 001 -> 100 transition must not become pending");

        pulse_pwm_boundary;

        if (hall_active !== 3'b001)
            fail("invalid transition must not change hall_active");


        // ============================================================
        // TEST 6: REVERSE COMMUTATION
        // ============================================================

        $display("");
        $display("TEST 6: Reverse Hall transition validation");

        reset_dut;

        dir = 1'b1;


        // Establish 001.

        set_hall(3'b001);
        wait_for_pending(3'b001);
        pulse_pwm_boundary;

        if (hall_active !== 3'b001)
            fail("reverse test failed to establish Hall 001");


        // 001 -> 011

        set_hall(3'b011);
        wait_for_pending(3'b011);

        if (hall_active !== 3'b001)
            fail("hall_active changed before reverse 001 -> 011 boundary");

        pulse_pwm_boundary;

        if (hall_active !== 3'b011)
            fail("reverse 001 -> 011 transition failed");


        // 011 -> 010

        set_hall(3'b010);
        wait_for_pending(3'b010);

        pulse_pwm_boundary;

        if (hall_active !== 3'b010)
            fail("reverse 011 -> 010 transition failed");


        // 010 -> 110

        set_hall(3'b110);
        wait_for_pending(3'b110);

        pulse_pwm_boundary;

        if (hall_active !== 3'b110)
            fail("reverse 010 -> 110 transition failed");


        // 110 -> 100

        set_hall(3'b100);
        wait_for_pending(3'b100);

        pulse_pwm_boundary;

        if (hall_active !== 3'b100)
            fail("reverse 110 -> 100 transition failed");


        // 100 -> 101

        set_hall(3'b101);
        wait_for_pending(3'b101);

        pulse_pwm_boundary;

        if (hall_active !== 3'b101)
            fail("reverse 100 -> 101 transition failed");


        // 101 -> 001

        set_hall(3'b001);
        wait_for_pending(3'b001);

        pulse_pwm_boundary;

        if (hall_active !== 3'b001)
            fail("reverse 101 -> 001 wrap transition failed");

        // ============================================================
        // TEST 7: LATEST VALID HALL WINS
        // ============================================================

        $display("");
        $display("TEST 7: Latest-valid-Hall-wins");

        reset_dut;

        dir = 1'b0;


        // Establish Hall 001.

        set_hall(3'b001);
        wait_for_pending(3'b001);
        pulse_pwm_boundary;

        if (hall_active !== 3'b001)
            fail("latest-Hall test failed to establish Hall 001");


        // ------------------------------------------------------------
        // 001 -> 101
        // ------------------------------------------------------------

        set_hall(3'b101);
        wait_for_pending(3'b101);

        if (!dut.pending_valid ||
            dut.hall_pending !== 3'b101)
            fail("101 did not become pending");

        if (hall_active !== 3'b001)
            fail("hall_active changed before PWM boundary");


        // ------------------------------------------------------------
        // 101 -> 100 BEFORE PWM BOUNDARY
        //
        // The active state is STILL 001.
        //
        // Therefore 100 must be validated against the pending 101,
        // not against the active 001.
        // ------------------------------------------------------------

        set_hall(3'b100);
        wait_for_pending(3'b100);

        if (!dut.pending_valid ||
            dut.hall_pending !== 3'b100)
            fail("latest valid Hall state did not replace 101");

        if (hall_active !== 3'b001)
            fail("hall_active changed before latest-Hall PWM boundary");


        // ------------------------------------------------------------
        // PWM boundary
        //
        // Only the latest pending state, 100, should become active.
        // ------------------------------------------------------------

        pulse_pwm_boundary;

        if (hall_active !== 3'b100)
            fail("latest pending Hall state was not committed");

        if (phase_cmd !== 6'b001001)
            fail("Hall 100 must command B+ C-");

        // ============================================================
        // TEST 8: INVALID HALL GRACE PERIOD AND FAULT
        // ============================================================

        $display("");
        $display("TEST 8: Invalid Hall grace period and fault");

        reset_dut;

        dir = 1'b0;


        // ------------------------------------------------------------
        // Establish a valid operating state.
        // ------------------------------------------------------------

        set_hall(3'b001);
        wait_for_pending(3'b001);
        pulse_pwm_boundary;

        if (hall_active !== 3'b001)
            fail("invalid-Hall test failed to establish Hall 001");

        if (hall_fault)
            fail("hall_fault must be clear during valid operation");


        // ------------------------------------------------------------
        // Apply invalid Hall state 000.
        //
        // The first invalid PWM period must consume the grace period,
        // but must NOT assert hall_fault.
        // ------------------------------------------------------------

        set_hall(3'b000);


        // Wait for the synchronized Hall state to become invalid.

        i = 0;

        while (hall_valid && (i < 20)) begin
            @(posedge clk);
            #1;
            i = i + 1;
        end

        if (hall_valid)
            fail("000 did not become an invalid synchronized Hall state");


        // First PWM boundary: consume the grace period.
        pulse_pwm_boundary;

        if (!dut.grace_used)
            fail("first invalid Hall period did not consume grace");

        if (hall_fault)
            fail("first invalid Hall period must not assert hall_fault");

        if (hall_active !== 3'b001)
            fail("invalid Hall must not change hall_active");


        // ------------------------------------------------------------
        // The Hall input is STILL invalid.
        //
        // Wait for the NEXT PWM boundary.
        //
        // The second consecutive invalid period must assert hall_fault.
        // ------------------------------------------------------------

        // Second consecutive PWM boundary: assert Hall fault.
        pulse_pwm_boundary;
        if (!hall_fault)
            fail("second consecutive invalid Hall period must assert hall_fault");


        // The invalid Hall state must never become active.

        if (hall_active !== 3'b001)
            fail("Hall fault must preserve the last valid hall_active state");

        // ============================================================
        // FINAL RESULT
        // ============================================================

        $display("");

        if (errors == 0)
            $display("PASS: hall_commutation unit verification");

        else
            $display(
                "FAIL: hall_commutation unit verification: %0d checks failed",
                errors
            );

        $finish;
    end

endmodule

output/simulation_artifacts/hall_commutation_tb.vcd
$date
	Mon Sep  7 21:45:46 2026
$end
$version
	Icarus Verilog
$end
$timescale
	1ps
$end
$scope module hall_commutation_tb $end
$var wire 6 ! phase_cmd [5:0] $end
$var wire 1 " hall_valid $end
$var wire 3 # hall_sync [2:0] $end
$var wire 1 $ hall_fault $end
$var wire 3 % hall_active [2:0] $end
$var reg 1 & clk $end
$var reg 1 ' dir $end
$var reg 1 ( hall_a $end
$var reg 1 ) hall_b $end
$var reg 1 * hall_c $end
$var reg 1 + pwm_boundary $end
$var reg 1 , reset_n $end
$var integer 32 - errors [31:0] $end
$var integer 32 . i [31:0] $end
$scope module dut $end
$var wire 1 & clk $end
$var wire 1 ' dir $end
$var wire 1 ( hall_a $end
$var wire 1 ) hall_b $end
$var wire 1 * hall_c $end
$var wire 1 " hall_valid $end
$var wire 1 + pwm_boundary $end
$var wire 1 , reset_n $end
$var wire 3 / transition_reference [2:0] $end
$var wire 3 0 hall_sync [2:0] $end
$var reg 1 1 bad_hall_observed $end
$var reg 1 2 grace_used $end
$var reg 2 3 hall_a_pipe [1:0] $end
$var reg 3 4 hall_active [2:0] $end
$var reg 2 5 hall_b_pipe [1:0] $end
$var reg 2 6 hall_c_pipe [1:0] $end
$var reg 1 $ hall_fault $end
$var reg 3 7 hall_pending [2:0] $end
$var reg 3 8 hall_previous [2:0] $end
$var reg 1 9 pending_valid $end
$var reg 6 : phase_cmd [5:0] $end
$scope function valid_transition $end
$var reg 1 ; direction $end
$var reg 3 < from_hall [2:0] $end
$var reg 3 = to_hall [2:0] $end
$upscope $end
$upscope $end
$scope task fail $end
$var reg 800 > message [799:0] $end
$upscope $end
$scope task pulse_pwm_boundary $end
$upscope $end
$scope task reset_dut $end
$upscope $end
$scope task set_hall $end
$var reg 3 ? hall_value [2:0] $end
$upscope $end
$scope task wait_for_pending $end
$var reg 3 @ expected_hall [2:0] $end
$upscope $end
$upscope $end
$enddefinitions $end
$comment Show the parameter values. $end
$dumpall
$end
#0
$dumpvars
bx @
bx ?
bx >
bx =
bx <
x;
b0 :
09
b0 8
b0 7
b0 6
b0 5
b0 4
b0 3
02
01
b0 0
b0 /
bx .
b0 -
0,
0+
0*
0)
0(
0'
0&
b0 %
0$
b0 #
0"
b0 !
$end
#10000
1&
#20000
0&
#30000
1&
#40000
0&
#50000
11
1,
1&
#60000
0&
#70000
1&
#80000
0&
#90000
1&
#100000
0&
#110000
1&
#111000
01
0,
#120000
0&
#130000
1&
#140000
0&
#150000
1&
#160000
0&
#170000
11
1,
1&
#180000
0&
#190000
1&
#200000
0&
#210000
1&
#220000
0&
#230000
1&
#231000
1*
b1 ?
#240000
0&
#250000
b1 6
1&
#260000
0&
#270000
1"
b1 #
b1 0
b11 6
1&
#280000
0&
#290000
b1 /
19
b1 7
b1 8
1&
#291000
1(
b101 ?
#300000
0&
#310000
b1 3
1&
#320000
0&
#330000
b101 #
b101 0
b11 3
1&
#340000
0&
#350000
b101 /
b101 7
b101 8
1&
#351000
0*
b100 ?
#360000
0&
#370000
b10 6
1&
#380000
0&
#390000
b100 #
b100 0
b0 6
1&
#400000
0&
#410000
b100 /
b100 7
b100 8
1&
#411000
1)
b110 ?
#420000
0&
#430000
b1 5
1&
#440000
0&
#450000
b110 #
b110 0
b11 5
1&
#460000
0&
#470000
b110 /
b110 7
b110 8
1&
#471000
0(
b10 ?
#480000
0&
#490000
b10 3
1&
#500000
0&
#510000
b10 #
b10 0
b0 3
1&
#520000
0&
#530000
b10 /
b10 7
b10 8
1&
#531000
1*
b11 ?
#540000
0&
#550000
b1 6
1&
#560000
0&
#570000
b11 #
b11 0
b11 6
1&
#580000
0&
#590000
b11 /
b11 7
b11 8
1&
#591000
1(
b111 ?
#600000
0&
#610000
b1 3
1&
#620000
0&
#630000
0"
b111 #
b111 0
b11 3
1&
#640000
0&
#650000
b111 8
1&
#651000
0(
0)
0*
b0 ?
#660000
0&
#670000
b10 6
b10 5
b10 3
1&
#680000
0&
#690000
b0 #
b0 0
b0 6
b0 5
b0 3
1&
#700000
0&
#710000
b0 8
1&
#711000
b0 /
01
09
b0 7
0,
#720000
0&
#730000
1&
#740000
0&
#750000
1&
#760000
0&
#770000
11
1,
1&
#780000
0&
#790000
1&
#800000
0&
#810000
1&
#820000
0&
#830000
1&
#831000
b0 .
b1 @
1*
b1 ?
#840000
0&
#850000
b1 6
1&
#851000
b1 .
#860000
0&
#870000
1"
b1 #
b1 0
b11 6
1&
#871000
b10 .
#880000
0&
#890000
b1 /
19
b1 7
b1 8
1&
#891000
1+
b11 .
#900000
0&
#910000
b100100 !
b100100 :
09
b1 %
b1 4
1&
#911000
b0 .
b101 @
1(
b101 ?
0+
#920000
0&
#930000
b1 3
1&
#931000
b1 .
#940000
0&
#950000
b101 #
b101 0
b11 3
1&
#951000
b10 .
#960000
0&
#970000
b101 /
19
b101 7
b101 8
b1 <
b101 =
0;
1&
#971000
1+
b11 .
#980000
0&
#990000
b100001 !
b100001 :
09
b101 %
b101 4
1&
#991000
b0 .
b100 @
0*
b100 ?
0+
#1000000
0&
#1010000
b10 6
1&
#1011000
b1 .
#1020000
0&
#1030000
b100 #
b100 0
b0 6
1&
#1031000
b10 .
#1040000
0&
#1050000
b100 /
19
b100 7
b100 8
b101 <
b100 =
1&
#1051000
1+
b11 .
#1060000
0&
#1070000
b1001 !
b1001 :
09
b100 %
b100 4
1&
#1071000
b0 .
b110 @
1)
b110 ?
0+
#1080000
0&
#1090000
b1 5
1&
#1091000
b1 .
#1100000
0&
#1110000
b110 #
b110 0
b11 5
1&
#1111000
b10 .
#1120000
0&
#1130000
b110 /
19
b110 7
b110 8
b100 <
b110 =
1&
#1131000
1+
b11 .
#1140000
0&
#1150000
b11000 !
b11000 :
09
b110 %
b110 4
1&
#1151000
b0 .
b10 @
0(
b10 ?
0+
#1160000
0&
#1170000
b10 3
1&
#1171000
b1 .
#1180000
0&
#1190000
b10 #
b10 0
b0 3
1&
#1191000
b10 .
#1200000
0&
#1210000
b10 /
19
b10 7
b10 8
b110 <
b10 =
1&
#1211000
1+
b11 .
#1220000
0&
#1230000
b10010 !
b10010 :
09
b10 %
b10 4
1&
#1231000
b0 .
b11 @
1*
b11 ?
0+
#1240000
0&
#1250000
b1 6
1&
#1251000
b1 .
#1260000
0&
#1270000
b11 #
b11 0
b11 6
1&
#1271000
b10 .
#1280000
0&
#1290000
b11 /
19
b11 7
b11 8
b10 <
b11 =
1&
#1291000
1+
b11 .
#1300000
0&
#1310000
b110 !
b110 :
09
b11 %
b11 4
1&
#1311000
b0 .
b1 @
0)
b1 ?
0+
#1320000
0&
#1330000
b10 5
1&
#1331000
b1 .
#1340000
0&
#1350000
1"
b1 #
b1 0
b0 5
1&
#1351000
b10 .
#1360000
0&
#1370000
b1 /
19
b1 7
b1 8
b11 <
b1 =
1&
#1371000
1+
b11 .
#1380000
0&
#1390000
b100100 !
b100100 :
09
b1 %
b1 4
1&
#1391000
1(
b101 ?
0+
#1400000
0&
#1410000
b1 3
1&
#1420000
0&
#1430000
b101 #
b101 0
b11 3
1&
#1440000
0&
#1450000
b101 /
19
b101 7
b101 8
b1 <
b101 =
1+
1&
#1460000
0&
#1470000
b100001 !
b100001 :
09
b101 %
b101 4
1&
#1471000
0*
b100 ?
0+
#1480000
0&
#1490000
b10 6
1&
#1500000
0&
#1510000
b100 #
b100 0
b0 6
1&
#1520000
0&
#1530000
b100 /
19
b100 7
b100 8
b101 <
b100 =
1+
1&
#1540000
0&
#1550000
b1001 !
b1001 :
09
b100 %
b100 4
1&
#1551000
1)
b110 ?
0+
#1560000
0&
#1570000
b1 5
1&
#1580000
0&
#1590000
b110 #
b110 0
b11 5
1&
#1600000
0&
#1610000
b110 /
19
b110 7
b110 8
b100 <
b110 =
1+
1&
#1620000
0&
#1630000
b11000 !
b11000 :
09
b110 %
b110 4
1&
#1631000
0(
b10 ?
0+
#1640000
0&
#1650000
b10 3
1&
#1660000
0&
#1670000
b10 #
b10 0
b0 3
1&
#1680000
0&
#1690000
b10 /
19
b10 7
b10 8
b110 <
b10 =
1+
1&
#1700000
0&
#1710000
b10010 !
b10010 :
09
b10 %
b10 4
1&
#1711000
1*
b11 ?
0+
#1720000
0&
#1730000
b1 6
1&
#1740000
0&
#1750000
b11 #
b11 0
b11 6
1&
#1760000
0&
#1770000
b11 /
19
b11 7
b11 8
b10 <
b11 =
1+
1&
#1780000
0&
#1790000
b110 !
b110 :
09
b11 %
b11 4
1&
#1791000
0"
b0 !
b0 :
b0 /
b0 #
b0 0
01
b0 %
b0 4
b0 7
b0 8
b0 6
b0 5
0,
0*
0)
0+
#1800000
0&
#1810000
1&
#1820000
0&
#1830000
1&
#1840000
0&
#1850000
11
1,
1&
#1860000
0&
#1870000
1&
#1880000
0&
#1890000
1&
#1900000
0&
#1910000
1&
#1911000
1*
b1 ?
#1920000
0&
#1930000
b1 6
1&
#1940000
0&
#1950000
1"
b1 #
b1 0
b11 6
1&
#1960000
0&
#1970000
b1 /
19
b1 7
b1 8
1+
1&
#1980000
0&
#1990000
b100100 !
b100100 :
09
b1 %
b1 4
1&
#1991000
1(
0*
b100 ?
0+
#2000000
0&
#2010000
b10 6
b1 3
1&
#2020000
0&
#2030000
b100 #
b100 0
b0 6
b11 3
1&
#2040000
0&
#2050000
b100 8
b1 <
b100 =
1+
1&
#2060000
0&
#2070000
1&
#2071000
0"
b0 #
b0 0
b0 !
b0 :
b0 /
b0 3
01
b0 %
b0 4
b0 7
b0 8
0,
0(
0+
#2080000
0&
#2090000
1&
#2100000
0&
#2110000
1&
#2120000
0&
#2130000
11
1,
1&
#2140000
0&
#2150000
1&
#2160000
0&
#2170000
1&
#2180000
0&
#2190000
1&
#2191000
b0 .
1*
b1 ?
1'
#2200000
0&
#2210000
b1 6
1&
#2211000
b1 .
#2220000
0&
#2230000
1"
b1 #
b1 0
b11 6
1&
#2231000
b10 .
#2240000
0&
#2250000
b1 /
19
b1 7
b1 8
1&
#2251000
1+
b11 .
#2260000
0&
#2270000
b100100 !
b100100 :
09
b1 %
b1 4
1&
#2271000
b0 .
b11 @
1)
b11 ?
0+
#2280000
0&
#2290000
b1 5
1&
#2291000
b1 .
#2300000
0&
#2310000
b11 #
b11 0
b11 5
1&
#2311000
b10 .
#2320000
0&
#2330000
b11 /
19
b11 7
b11 8
b11 =
1;
1&
#2331000
1+
b11 .
#2340000
0&
#2350000
b110 !
b110 :
09
b11 %
b11 4
1&
#2351000
b0 .
b10 @
0*
b10 ?
0+
#2360000
0&
#2370000
b10 6
1&
#2371000
b1 .
#2380000
0&
#2390000
1"
b10 #
b10 0
b0 6
1&
#2391000
b10 .
#2400000
0&
#2410000
b10 /
19
b10 7
b10 8
b11 <
b10 =
1&
#2411000
1+
b11 .
#2420000
0&
#2430000
b10010 !
b10010 :
09
b10 %
b10 4
1&
#2431000
b0 .
b110 @
1(
b110 ?
0+
#2440000
0&
#2450000
b1 3
1&
#2451000
b1 .
#2460000
0&
#2470000
1"
b110 #
b110 0
b11 3
1&
#2471000
b10 .
#2480000
0&
#2490000
b110 /
19
b110 7
b110 8
b10 <
b110 =
1&
#2491000
1+
b11 .
#2500000
0&
#2510000
b11000 !
b11000 :
09
b110 %
b110 4
1&
#2511000
b0 .
b100 @
0)
b100 ?
0+
#2520000
0&
#2530000
b10 5
1&
#2531000
b1 .
#2540000
0&
#2550000
1"
b100 #
b100 0
b0 5
1&
#2551000
b10 .
#2560000
0&
#2570000
b100 /
19
b100 7
b100 8
b110 <
b100 =
1&
#2571000
1+
b11 .
#2580000
0&
#2590000
b1001 !
b1001 :
09
b100 %
b100 4
1&
#2591000
b0 .
b101 @
1*
b101 ?
0+
#2600000
0&
#2610000
b1 6
1&
#2611000
b1 .
#2620000
0&
#2630000
1"
b101 #
b101 0
b11 6
1&
#2631000
b10 .
#2640000
0&
#2650000
b101 /
19
b101 7
b101 8
b100 <
b101 =
1&
#2651000
1+
b11 .
#2660000
0&
#2670000
b100001 !
b100001 :
09
b101 %
b101 4
1&
#2671000
b0 .
b1 @
0(
b1 ?
0+
#2680000
0&
#2690000
b10 3
1&
#2691000
b1 .
#2700000
0&
#2710000
b1 #
b1 0
b0 3
1&
#2711000
b10 .
#2720000
0&
#2730000
b1 /
19
b1 7
b1 8
b101 <
b1 =
1&
#2731000
1+
b11 .
#2740000
0&
#2750000
b100100 !
b100100 :
09
b1 %
b1 4
1&
#2751000
0"
b0 !
b0 :
b0 /
b0 #
b0 0
01
b0 %
b0 4
b0 7
b0 8
b0 6
0,
0'
0*
0+
#2760000
0&
#2770000
1&
#2780000
0&
#2790000
1&
#2800000
0&
#2810000
11
1,
1&
#2820000
0&
#2830000
1&
#2840000
0&
#2850000
1&
#2860000
0&
#2870000
1&
#2871000
b0 .
1*
#2880000
0&
#2890000
b1 6
1&
#2891000
b1 .
#2900000
0&
#2910000
1"
b1 #
b1 0
b11 6
1&
#2911000
b10 .
#2920000
0&
#2930000
b1 /
19
b1 7
b1 8
1&
#2931000
1+
b11 .
#2940000
0&
#2950000
b100100 !
b100100 :
09
b1 %
b1 4
1&
