src/pwm_generator.v
`timescale 1ns/1ps

module pwm_generator #(
    parameter [10:0] PWM_PERIOD_CLKS = 11'd1250
) (
    input  wire        clk,
    input  wire        reset_n,
    input  wire [9:0]  duty,
    output reg  [10:0] pwm_counter,
    output reg  [9:0]  duty_shadow,
    output reg  [9:0]  duty_active,
    output reg  [10:0] compare_value,
    output wire        pwm_raw,
    output wire        pwm_boundary
);
    // The product is at most 1,278,750.  The extra bits retain explicit
    // arithmetic sizing across conservative Verilog-2001 elaborators.
    localparam [10:0] PWM_LAST_COUNT = PWM_PERIOD_CLKS - 11'd1;
    reg [20:0] duty_scaled;

    assign pwm_boundary = (pwm_counter == PWM_LAST_COUNT);
    assign pwm_raw = (pwm_counter < compare_value);

    always @(*) begin
        duty_scaled =
            (duty_active << 10) +
            (duty_active << 7)  +
            (duty_active << 6)  +
            (duty_active << 5)  +
            (duty_active << 1);

        if (duty_active == 10'd1023)
            compare_value = 11'd1250;
        else
            compare_value = duty_scaled >> 10;
    end
    always @(posedge clk or negedge reset_n) begin
        if (!reset_n) begin
            pwm_counter <= 11'd0;
            duty_shadow <= 10'd0;
            duty_active <= 10'd0;
        end else begin
            duty_shadow <= duty;
            if (pwm_boundary) begin
                pwm_counter <= 11'd0;
                duty_active <= duty_shadow;
            end else begin
                pwm_counter <= pwm_counter + 11'd1;
            end
        end
    end
endmodule

testbench/pwm_generator_tb.v
`timescale 1ns/1ps

module pwm_generator_tb;

    reg clk;
    reg reset_n;
    reg [9:0] duty;

    wire [10:0] pwm_counter;
    wire [9:0] duty_shadow;
    wire [9:0] duty_active;
    wire [10:0] compare_value;
    wire pwm_raw;
    wire pwm_boundary;

    integer errors;
    integer i;
    integer high_count;
    integer boundary_count;

    pwm_generator #(
        .PWM_PERIOD_CLKS(11'd1250)
    ) dut (
        .clk           (clk),
        .reset_n       (reset_n),
        .duty          (duty),
        .pwm_counter   (pwm_counter),
        .duty_shadow   (duty_shadow),
        .duty_active   (duty_active),
        .compare_value (compare_value),
        .pwm_raw       (pwm_raw),
        .pwm_boundary  (pwm_boundary)
    );

    always #10 clk = ~clk;


    task fail;
        input [8*100-1:0] message;
        begin
            errors = errors + 1;
            $display("FAIL: %0s", message);
        end
    endtask


    task reset_dut;
        begin
            duty    = 10'd0;
            reset_n = 1'b0;

            #1;

            if (pwm_counter !== 11'd0)
                fail("reset must clear pwm_counter");

            if (duty_shadow !== 10'd0)
                fail("reset must clear duty_shadow");

            if (duty_active !== 10'd0)
                fail("reset must clear duty_active");

            if (compare_value !== 11'd0)
                fail("reset must produce compare value 0");

            if (pwm_raw !== 1'b0)
                fail("reset must produce PWM low");

            repeat (3)
                @(posedge clk);

            reset_n = 1'b1;

            repeat (3) begin
                @(posedge clk);
                #1;
            end
        end
    endtask


    task wait_for_boundary;
        begin
            i = 0;

            while (!pwm_boundary && (i < 1300)) begin
                @(posedge clk);
                #1;
                i = i + 1;
            end

            if (!pwm_boundary)
                fail("PWM boundary was not reached");
        end
    endtask


    initial begin

        clk     = 1'b0;
        reset_n = 1'b0;
        duty    = 10'd0;
        errors  = 0;


        $dumpfile("output/pwm_generator_tb.vcd");
        $dumpvars(0, pwm_generator_tb);


        // ============================================================
        // TEST 1: RESET
        // ============================================================

        $display("");
        $display("TEST 1: Reset");

        reset_dut;


        // ============================================================
        // TEST 2: PWM PERIOD
        // ============================================================

        $display("");
        $display("TEST 2: PWM period and boundary");

        reset_dut;

        // reset_dut releases reset and allows a few clocks to pass,
        // so the counter is not expected to still be zero here.

        // Count complete PWM periods.
        boundary_count = 0;

        for (i = 0; i < 2500; i = i + 1) begin
            @(posedge clk);
            #1;

            if (pwm_boundary)
                boundary_count = boundary_count + 1;
        end

        if (boundary_count !== 2)
            fail("1250-clock PWM must produce exactly two boundaries in 2500 clocks");


        // ============================================================
        // TEST 3: PWM COUNTER SEQUENCE
        // ============================================================

        $display("");
        $display("TEST 3: PWM counter sequence");

        reset_dut;

        // Align to the next actual counter-zero state.
        i = 0;

        while ((pwm_counter !== 11'd0) && (i < 1300)) begin
            @(posedge clk);
            #1;
            i = i + 1;
        end

        if (pwm_counter !== 11'd0)
            fail("PWM counter did not return to zero");

        // Verify 0 -> 1.
        @(posedge clk);
        #1;

        if (pwm_counter !== 11'd1)
            fail("PWM counter must increment from 0 to 1");

        // Verify the counter reaches 1248.
        // We are currently at 1, so 1247 further clock edges
        // should bring it to 1248.
        for (i = 0; i < 1247; i = i + 1) begin
            @(posedge clk);
            #1;
        end

        if (pwm_counter !== 11'd1248)
            fail("PWM counter did not reach 1248 correctly");

        // Next clock must produce 1249.
        @(posedge clk);
        #1;

        if (pwm_counter !== 11'd1249)
            fail("PWM counter must reach 1249 before wrapping");

        // At counter 1249, pwm_boundary must be asserted.
        if (!pwm_boundary)
            fail("PWM boundary must be asserted at counter 1249");

        // Next clock wraps to zero.
        @(posedge clk);
        #1;

        if (pwm_counter !== 11'd0)
            fail("PWM counter must wrap from 1249 to 0");

        // ============================================================
        // TEST 4: DUTY SHADOW / ACTIVE TRANSFER
        // ============================================================

        $display("");
        $display("TEST 4: Boundary-aligned duty transfer");

        reset_dut;

        duty = 10'd512;

        // duty_shadow should capture DUTY on a clock edge.
        @(posedge clk);
        #1;

        if (duty_shadow !== 10'd512)
            fail("DUTY must transfer into duty_shadow");

        // duty_active must not change immediately.
        if (duty_active !== 10'd0)
            fail("duty_active must remain unchanged before PWM boundary");

        // Wait until the boundary.
        wait_for_boundary;

        // At the boundary, duty_active is loaded from duty_shadow.
        @(posedge clk);
        #1;

        if (duty_active !== 10'd512)
            fail("duty_active must update at PWM boundary");


        // ============================================================
        // TEST 5: DUTY 0
        // ============================================================

        $display("");
        $display("TEST 5: DUTY 0");

        duty = 10'd0;

        wait_for_boundary;

        @(posedge clk);
        #1;

        if (duty_active !== 10'd0)
            fail("DUTY 0 must transfer to duty_active");

        if (compare_value !== 11'd0)
            fail("DUTY 0 must map to compare value 0");

        if (pwm_raw)
            fail("DUTY 0 must keep PWM low");


        // ============================================================
        // TEST 6: DUTY 512
        // ============================================================

        $display("");
        $display("TEST 6: DUTY 512 compare mapping");

        duty = 10'd512;

        wait_for_boundary;

        @(posedge clk);
        #1;

        if (duty_active !== 10'd512)
            fail("DUTY 512 must transfer to duty_active");

        if (compare_value !== 11'd625)
            fail("DUTY 512 must map to compare value 625");


        // ============================================================
        // TEST 7: DUTY 1023
        // ============================================================

        $display("");
        $display("TEST 7: DUTY 1023 compare mapping");

        duty = 10'd1023;

        wait_for_boundary;

        @(posedge clk);
        #1;

        if (duty_active !== 10'd1023)
            fail("DUTY 1023 must transfer to duty_active");

        if (compare_value !== 11'd1250)
            fail("DUTY 1023 must map to compare value 1250");


        // ============================================================
        // TEST 8: EXACT PWM HIGH COUNT
        // ============================================================

        $display("");
        $display("TEST 8: Exact PWM high interval count");

        reset_dut;

        duty = 10'd512;

        wait_for_boundary;

        @(posedge clk);
        #1;

        if (duty_active !== 10'd512)
            fail("DUTY 512 was not activated");

        if (compare_value !== 11'd625)
            fail("DUTY 512 compare value incorrect");

        // Align to counter zero.
        while (pwm_counter !== 11'd0) begin
            @(posedge clk);
            #1;
        end

        high_count = 0;

        for (i = 0; i < 1250; i = i + 1) begin

            if (pwm_raw)
                high_count = high_count + 1;

            @(posedge clk);
            #1;
        end

        if (high_count !== 625)
            fail("DUTY 512 must produce exactly 625 high intervals");


        // ============================================================
        // TEST 9: 100% PWM
        // ============================================================

        $display("");
        $display("TEST 9: 100 percent PWM");

        duty = 10'd1023;

        wait_for_boundary;

        @(posedge clk);
        #1;

        if (compare_value !== 11'd1250)
            fail("100 percent duty must produce compare value 1250");

        while (pwm_counter !== 11'd0) begin
            @(posedge clk);
            #1;
        end

        high_count = 0;

        for (i = 0; i < 1250; i = i + 1) begin

            if (pwm_raw)
                high_count = high_count + 1;

            @(posedge clk);
            #1;
        end

        if (high_count !== 1250)
            fail("100 percent duty must produce 1250 high intervals");


        // ============================================================
        // TEST 10: 0 PERCENT PWM
        // ============================================================

        $display("");
        $display("TEST 10: 0 percent PWM");

        duty = 10'd0;

        wait_for_boundary;

        @(posedge clk);
        #1;

        if (compare_value !== 11'd0)
            fail("0 percent duty must produce compare value 0");

        while (pwm_counter !== 11'd0) begin
            @(posedge clk);
            #1;
        end

        high_count = 0;

        for (i = 0; i < 1250; i = i + 1) begin

            if (pwm_raw)
                high_count = high_count + 1;

            @(posedge clk);
            #1;
        end

        if (high_count !== 0)
            fail("0 percent duty must produce zero high intervals");


        // ============================================================
        // FINAL RESULT
        // ============================================================

        $display("");

        if (errors == 0)
            $display("PASS: pwm_generator unit verification");
        else
            $display(
                "FAIL: pwm_generator unit verification: %0d checks failed",
                errors
            );

        $finish;

    end

endmodule

output/simulation_artifacts/pwm_generator_tb.vcd
$date
	Mon Sep 28 05:02:15 2026
$end
$version
	Icarus Verilog
$end
$timescale
	1ps
$end
$scope module pwm_generator_tb $end
$var wire 1 ! pwm_raw $end
$var wire 11 " pwm_counter [10:0] $end
$var wire 1 # pwm_boundary $end
$var wire 10 $ duty_shadow [9:0] $end
$var wire 10 % duty_active [9:0] $end
$var wire 11 & compare_value [10:0] $end
$var reg 1 ' clk $end
$var reg 10 ( duty [9:0] $end
$var reg 1 ) reset_n $end
$var integer 32 * boundary_count [31:0] $end
$var integer 32 + errors [31:0] $end
$var integer 32 , high_count [31:0] $end
$var integer 32 - i [31:0] $end
$scope module dut $end
$var wire 1 ' clk $end
$var wire 10 . duty [9:0] $end
$var wire 1 ) reset_n $end
$var wire 1 ! pwm_raw $end
$var wire 1 # pwm_boundary $end
$var parameter 11 / PWM_LAST_COUNT $end
$var parameter 11 0 PWM_PERIOD_CLKS $end
$var reg 11 1 compare_value [10:0] $end
$var reg 10 2 duty_active [9:0] $end
$var reg 21 3 duty_scaled [20:0] $end
$var reg 10 4 duty_shadow [9:0] $end
$var reg 11 5 pwm_counter [10:0] $end
$upscope $end
$scope task fail $end
$var reg 800 6 message [799:0] $end
$upscope $end
$scope task reset_dut $end
$upscope $end
$scope task wait_for_boundary $end
$upscope $end
$upscope $end
$enddefinitions $end
$comment Show the parameter values. $end
$dumpall
b10011100010 0
b10011100001 /
$end
#0
$dumpvars
bx 6
b0 5
b0 4
b0 3
b0 2
b0 1
b0 .
bx -
bx ,
b0 +
bx *
0)
b0 (
0'
b0 &
b0 %
b0 $
0#
b0 "
0!
$end
#10000
1'
#20000
0'
#30000
1'
#40000
0'
#50000
b1 "
b1 5
1)
1'
#60000
0'
#70000
b10 "
b10 5
1'
#80000
0'
#90000
b11 "
b11 5
1'
#100000
0'
#110000
b100 "
b100 5
1'
#111000
b0 "
b0 5
0)
#120000
0'
#130000
1'
#140000
0'
#150000
1'
#160000
0'
#170000
b1 "
b1 5
1)
1'
#180000
0'
#190000
b10 "
b10 5
1'
#200000
0'
#210000
b11 "
b11 5
1'
#220000
0'
#230000
b100 "
b100 5
1'
#231000
b0 -
b0 *
#240000
0'
#250000
b101 "
b101 5
1'
#251000
b1 -
#260000
0'
#270000
b110 "
b110 5
1'
#271000
b10 -
#280000
0'
#290000
b111 "
b111 5
1'
#291000
b11 -
#300000
0'
#310000
b1000 "
b1000 5
1'
#311000
b100 -
#320000
0'
#330000
b1001 "
b1001 5
1'
#331000
b101 -
#340000
0'
#350000
b1010 "
b1010 5
1'
#351000
b110 -
#360000
0'
#370000
b1011 "
b1011 5
1'
#371000
b111 -
#380000
0'
#390000
b1100 "
b1100 5
1'
#391000
b1000 -
#400000
0'
#410000
b1101 "
b1101 5
1'
#411000
b1001 -
#420000
0'
#430000
b1110 "
b1110 5
1'
#431000
b1010 -
#440000
0'
#450000
b1111 "
b1111 5
1'
#451000
b1011 -
#460000
0'
#470000
b10000 "
b10000 5
1'
#471000
b1100 -
#480000
0'
#490000
b10001 "
b10001 5
1'
#491000
b1101 -
#500000
0'
#510000
b10010 "
b10010 5
1'
#511000
b1110 -
#520000
0'
#530000
b10011 "
b10011 5
1'
#531000
b1111 -
#540000
0'
#550000
b10100 "
b10100 5
1'
#551000
b10000 -
#560000
0'
#570000
b10101 "
b10101 5
1'
#571000
b10001 -
#580000
0'
#590000
b10110 "
b10110 5
1'
#591000
b10010 -
#600000
0'
#610000
b10111 "
b10111 5
1'
#611000
b10011 -
#620000
0'
#630000
b11000 "
b11000 5
1'
#631000
b10100 -
#640000
0'
#650000
b11001 "
b11001 5
1'
#651000
b10101 -
#660000
0'
#670000
b11010 "
b11010 5
1'
#671000
b10110 -
#680000
0'
#690000
b11011 "
b11011 5
1'
#691000
b10111 -
#700000
0'
#710000
b11100 "
b11100 5
1'
#711000
b11000 -
#720000
0'
#730000
b11101 "
b11101 5
1'
#731000
b11001 -
#740000
0'
#750000
b11110 "
b11110 5
1'
#751000
b11010 -
#760000
0'
#770000
b11111 "
b11111 5
1'
#771000
b11011 -
#780000
0'
#790000
b100000 "
b100000 5
1'
#791000
b11100 -
#800000
0'
#810000
b100001 "
b100001 5
1'
#811000
b11101 -
#820000
0'
#830000
b100010 "
b100010 5
1'
#831000
b11110 -
#840000
0'
#850000
b100011 "
b100011 5
1'
#851000
b11111 -
#860000
0'
#870000
b100100 "
b100100 5
1'
#871000
b100000 -
#880000
0'
#890000
b100101 "
b100101 5
1'
#891000
b100001 -
#900000
0'
#910000
b100110 "
b100110 5
1'
#911000
b100010 -
#920000
0'
#930000
b100111 "
b100111 5
1'
#931000
b100011 -
#940000
0'
#950000
b101000 "
b101000 5
1'
#951000
b100100 -
#960000
0'
#970000
b101001 "
b101001 5
1'
#971000
b100101 -
#980000
0'
#990000
b101010 "
b101010 5
1'
#991000
b100110 -
#1000000
0'
#1010000
b101011 "
b101011 5
1'
#1011000
b100111 -
#1020000
0'
#1030000
b101100 "
b101100 5
1'
#1031000
b101000 -
#1040000
0'
#1050000
b101101 "
b101101 5
1'
#1051000
b101001 -
#1060000
0'
#1070000
b101110 "
b101110 5
1'
#1071000
b101010 -
#1080000
0'
#1090000
b101111 "
b101111 5
1'
#1091000
b101011 -
#1100000
0'
#1110000
b110000 "
b110000 5
1'
#1111000
b101100 -
#1120000
0'
#1130000
b110001 "
b110001 5
1'
#1131000
b101101 -
#1140000
0'
#1150000
b110010 "
b110010 5
1'
#1151000
b101110 -
#1160000
0'
#1170000
b110011 "
b110011 5
1'
#1171000
b101111 -
#1180000
0'
#1190000
b110100 "
b110100 5
1'
#1191000
b110000 -
#1200000
0'
#1210000
b110101 "
b110101 5
1'
#1211000
b110001 -
#1220000
0'
#1230000
b110110 "
b110110 5
1'
#1231000
b110010 -
#1240000
0'
#1250000
b110111 "
b110111 5
1'
#1251000
b110011 -
#1260000
0'
#1270000
b111000 "
b111000 5
1'
#1271000
b110100 -
#1280000
0'
#1290000
b111001 "
b111001 5
1'
#1291000
b110101 -
#1300000
0'
#1310000
b111010 "
b111010 5
1'
#1311000
b110110 -
#1320000
0'
#1330000
b111011 "
b111011 5
1'
#1331000
b110111 -
#1340000
0'
#1350000
b111100 "
b111100 5
1'
#1351000
b111000 -
#1360000
0'
#1370000
b111101 "
b111101 5
1'
#1371000
b111001 -
#1380000
0'
#1390000
b111110 "
b111110 5
1'
#1391000
b111010 -
#1400000
0'
#1410000
b111111 "
b111111 5
1'
#1411000
b111011 -
#1420000
0'
#1430000
b1000000 "
b1000000 5
1'
#1431000
b111100 -
#1440000
0'
#1450000
b1000001 "
b1000001 5
1'
#1451000
b111101 -
#1460000
0'
#1470000
b1000010 "
b1000010 5
1'
#1471000
b111110 -
#1480000
0'
#1490000
b1000011 "
b1000011 5
1'
#1491000
b111111 -
#1500000
0'
#1510000
b1000100 "
b1000100 5
1'
#1511000
b1000000 -
#1520000
0'
#1530000
b1000101 "
b1000101 5
1'
#1531000
b1000001 -
#1540000
0'
#1550000
b1000110 "
b1000110 5
1'
#1551000
b1000010 -
#1560000
0'
#1570000
b1000111 "
b1000111 5
1'
#1571000
b1000011 -
#1580000
0'
#1590000
b1001000 "
b1001000 5
1'
#1591000
b1000100 -
#1600000
0'
#1610000
b1001001 "
b1001001 5
1'
#1611000
b1000101 -
#1620000
0'
#1630000
b1001010 "
b1001010 5
1'
#1631000
b1000110 -
#1640000
0'
#1650000
b1001011 "
b1001011 5
1'
#1651000
b1000111 -
#1660000
0'
#1670000
b1001100 "
b1001100 5
1'
#1671000
b1001000 -
#1680000
0'
#1690000
b1001101 "
b1001101 5
1'
#1691000
b1001001 -
#1700000
0'
#1710000
b1001110 "
b1001110 5
1'
#1711000
b1001010 -
#1720000
0'
#1730000
b1001111 "
b1001111 5
1'
#1731000
b1001011 -
#1740000
0'
#1750000
b1010000 "
b1010000 5
1'
#1751000
b1001100 -
#1760000
0'
#1770000
b1010001 "
b1010001 5
1'
#1771000
b1001101 -
#1780000
0'
#1790000
b1010010 "
b1010010 5
1'
#1791000
b1001110 -
#1800000
0'
#1810000
b1010011 "
b1010011 5
1'
#1811000
b1001111 -
#1820000
0'
#1830000
b1010100 "
b1010100 5
1'
#1831000
b1010000 -
#1840000
0'
#1850000
b1010101 "
b1010101 5
1'
#1851000
b1010001 -
#1860000
0'
#1870000
b1010110 "
b1010110 5
1'
#1871000
b1010010 -
#1880000
0'
#1890000
b1010111 "
b1010111 5
1'
#1891000
b1010011 -
#1900000
0'
#1910000
b1011000 "
b1011000 5
1'
#1911000
b1010100 -
#1920000
0'
#1930000
b1011001 "
b1011001 5
1'
#1931000
b1010101 -
#1940000
0'
#1950000
b1011010 "
b1011010 5
1'
#1951000
b1010110 -
#1960000
0'
#1970000
b1011011 "
b1011011 5
1'
#1971000
b1010111 -
#1980000
0'
#1990000
b1011100 "
b1011100 5
1'
#1991000
b1011000 -
#2000000
0'
#2010000
b1011101 "
b1011101 5
1'
#2011000
b1011001 -
#2020000
0'
#2030000
b1011110 "
b1011110 5
1'
#2031000
b1011010 -
#2040000
0'
#2050000
b1011111 "
b1011111 5
1'
#2051000
b1011011 -
#2060000
0'
#2070000
b1100000 "
b1100000 5
1'
#2071000
b1011100 -
#2080000
0'
#2090000
b1100001 "
b1100001 5
1'
#2091000
b1011101 -
#2100000
0'
#2110000
b1100010 "
b1100010 5
1'
#2111000
b1011110 -
#2120000
0'
#2130000
b1100011 "
b1100011 5
1'
#2131000
b1011111 -
#2140000
0'
#2150000
b1100100 "
b1100100 5
1'
#2151000
b1100000 -
#2160000
0'
#2170000
b1100101 "
b1100101 5
1'
#2171000
b1100001 -
#2180000
0'
#2190000
b1100110 "
b1100110 5
1'
#2191000
b1100010 -
#2200000
0'
#2210000
b1100111 "
b1100111 5
1'
#2211000
b1100011 -
#2220000
0'
#2230000
b1101000 "
b1101000 5
1'
#2231000
b1100100 -
#2240000
0'
#2250000
b1101001 "
b1101001 5
1'
#2251000
b1100101 -
#2260000
0'
#2270000
b1101010 "
b1101010 5
1'
#2271000
b1100110 -
#2280000
0'
#2290000
b1101011 "
b1101011 5
1'
#2291000
b1100111 -
#2300000
0'
#2310000
b1101100 "
b1101100 5
1'
#2311000
b1101000 -
#2320000
0'
#2330000
b1101101 "
b1101101 5
1'
#2331000
b1101001 -
#2340000
0'
#2350000
b1101110 "
b1101110 5
1'
#2351000
b1101010 -
#2360000
0'
#2370000
b1101111 "
b1101111 5
1'
#2371000
b1101011 -
#2380000
0'
#2390000
b1110000 "
b1110000 5
1'
#2391000
b1101100 -
#2400000
0'
#2410000
b1110001 "
b1110001 5
1'
#2411000
b1101101 -
#2420000
0'
#2430000
b1110010 "
b1110010 5
1'
#2431000
b1101110 -
#2440000
0'
#2450000
b1110011 "
b1110011 5
1'
#2451000
b1101111 -
#2460000
0'
#2470000
b1110100 "
b1110100 5
1'
#2471000
b1110000 -
#2480000
0'
#2490000
b1110101 "
b1110101 5
1'
#2491000
b1110001 -
#2500000
0'
#2510000
b1110110 "
b1110110 5
1'
#2511000
b1110010 -
#2520000
0'
#2530000
b1110111 "
b1110111 5
1'
#2531000
b1110011 -
#2540000
0'
#2550000
b1111000 "
b1111000 5
1'
#2551000
b1110100 -
#2560000
0'
#2570000
b1111001 "
b1111001 5
1'
#2571000
b1110101 -
#2580000
0'
#2590000
b1111010 "
b1111010 5
1'
#2591000
b1110110 -
#2600000
0'
#2610000
b1111011 "
b1111011 5
1'
#2611000
b1110111 -
#2620000
0'
#2630000
b1111100 "
b1111100 5
1'
#2631000
b1111000 -
#2640000
0'
#2650000
b1111101 "
b1111101 5
1'
#2651000
b1111001 -
#2660000
0'
#2670000
b1111110 "
b1111110 5
1'
#2671000
b1111010 -
#2680000
0'
#2690000
b1111111 "
b1111111 5
1'
#2691000
b1111011 -
#2700000
0'
#2710000
b10000000 "
b10000000 5
1'
#2711000
b1111100 -
#2720000
0'
#2730000
b10000001 "
b10000001 5
1'
#2731000
b1111101 -
#2740000
0'
#2750000
b10000010 "
b10000010 5
1'
#2751000
b1111110 -
#2760000
0'
#2770000
b10000011 "
b10000011 5
1'
#2771000
b1111111 -
#2780000
0'
#2790000
b10000100 "
b10000100 5
1'
#2791000
b10000000 -
#2800000
0'
#2810000
b10000101 "
b10000101 5
1'
#2811000
b10000001 -
#2820000
0'
#2830000
b10000110 "
b10000110 5
1'
#2831000
b10000010 -
#2840000
0'
#2850000
b10000111 "
b10000111 5
1'
#2851000
b10000011 -
#2860000
0'
#2870000
b10001000 "
b10001000 5
1'
#2871000
b10000100 -
#2880000
0'
#2890000
b10001001 "
b10001001 5
1'
#2891000
b10000101 -
#2900000
0'
#2910000
b10001010 "
b10001010 5
1'
#2911000
b10000110 -
#2920000
0'
#2930000
b10001011 "
b10001011 5
1'
#2931000
b10000111 -
#2940000
0'
#2950000
b10001100 "
b10001100 5
1'
#2951000
b10001000 -
#2960000
0'
#2970000
b10001101 "
b10001101 5
1'
#2971000
b10001001 -
#2980000
0'
#2990000
b10001110 "
b10001110 5
1'
#2991000
b10001010 -
#3000000
0'
#3010000
b10001111 "
b10001111 5
1'
#3011000
b10001011 -
#3020000
0'
#3030000
b10010000 "
b10010000 5
1'
#3031000
b10001100 -
#3040000
0'
#3050000
b10010001 "
b10010001 5
1'
#3051000
b10001101 -
#3060000
0'
#3070000
b10010010 "
b10010010 5
1'
#3071000
b10001110 -
#3080000
0'
#3090000
b10010011 "
b10010011 5
1'
#3091000
b10001111 -
#3100000
0'
#3110000
b10010100 "
b10010100 5
1'
#3111000
b10010000 -
#3120000
0'
#3130000
b10010101 "
b10010101 5
1'
#3131000
b10010001 -
#3140000
0'
#3150000
b10010110 "
b10010110 5
1'
#3151000
b10010010 -
#3160000
0'
#3170000
b10010111 "
b10010111 5
1'
#3171000
b10010011 -
#3180000
0'
#3190000
b10011000 "
b10011000 5
1'
#3191000
b10010100 -
#3200000
0'
#3210000
b10011001 "
b10011001 5
1'
#3211000
b10010101 -
#3220000
0'
#3230000
b10011010 "
b10011010 5
1'
#3231000
b10010110 -
#3240000
0'
#3250000
b10011011 "
b10011011 5
1'
#3251000
b10010111 -
#3260000
0'
#3270000
b10011100 "
b10011100 5
1'
#3271000
b10011000 -
#3280000
0'
#3290000
b10011101 "
b10011101 5
1'
#3291000
b10011001 -
#3300000
0'
#3310000
b10011110 "
b10011110 5
1'
#3311000
b10011010 -
#3320000
0'
#3330000
b10011111 "
b10011111 5
1'
#3331000
b10011011 -
#3340000
0'
#3350000
b10100000 "
b10100000 5
1'
#3351000
b10011100 -
#3360000
0'
#3370000
b10100001 "
b10100001 5
1'
#3371000
b10011101 -
#3380000
0'
#3390000
b10100010 "
b10100010 5
1'
#3391000
b10011110 -
#3400000
0'
#3410000
b10100011 "
b10100011 5
1'
#3411000
b10011111 -
#3420000
0'
#3430000
b10100100 "
b10100100 5
1'
#3431000
b10100000 -
#3440000
0'
#3450000
b10100101 "
b10100101 5
1'
#3451000
b10100001 -
#3460000
0'
#3470000
b10100110 "
b10100110 5
1'
#3471000
b10100010 -
#3480000
0'
#3490000
b10100111 "
b10100111 5
1'
#3491000
b10100011 -
#3500000
0'
#3510000
b10101000 "
b10101000 5
1'
#3511000
b10100100 -
#3520000
0'
#3530000
b10101001 "
b10101001 5
1'
#3531000
b10100101 -
#3540000
0'
#3550000
b10101010 "
b10101010 5
1'
#3551000
b10100110 -
#3560000
0'
#3570000
b10101011 "
b10101011 5
1'
#3571000
b10100111 -
#3580000
0'
#3590000
b10101100 "
b10101100 5
1'
#3591000
b10101000 -
#3600000
0'
#3610000
b10101101 "
b10101101 5
1'
#3611000
b10101001 -
#3620000
0'
#3630000
b10101110 "
b10101110 5
1'
#3631000
b10101010 -
#3640000
0'
#3650000
b10101111 "
b10101111 5
1'
#3651000
b10101011 -
#3660000
0'
#3670000
b10110000 "
b10110000 5
1'
#3671000
b10101100 -
#3680000
0'
#3690000
b10110001 "
b10110001 5
1'
#3691000
b10101101 -
#3700000
0'
#3710000
b10110010 "
b10110010 5
1'
#3711000
b10101110 -
#3720000
0'
#3730000
b10110011 "
b10110011 5
1'
#3731000
b10101111 -
#3740000
0'
#3750000
b10110100 "
b10110100 5
1'
#3751000
b10110000 -
#3760000
0'
#3770000
b10110101 "
b10110101 5
1'
#3771000
b10110001 -
#3780000
0'
#3790000
b10110110 "
b10110110 5
1'
#3791000
b10110010 -
#3800000
0'
#3810000
b10110111 "
b10110111 5
1'
#3811000
b10110011 -
#3820000
0'
#3830000
b10111000 "
b10111000 5
1'
#3831000
b10110100 -
#3840000
0'
#3850000
b10111001 "
b10111001 5
1'
#3851000
b10110101 -
#3860000
0'
#3870000
b10111010 "
b10111010 5
1'
#3871000
b10110110 -
#3880000
0'
#3890000
b10111011 "
b10111011 5
1'
#3891000
b10110111 -
#3900000
0'
#3910000
b10111100 "
b10111100 5
1'
#3911000
b10111000 -
#3920000
0'
#3930000
b10111101 "
b10111101 5
1'
#3931000
b10111001 -
#3940000
0'
#3950000
b10111110 "
b10111110 5
1'
#3951000
b10111010 -
#3960000
0'
#3970000
b10111111 "
b10111111 5
1'
#3971000
b10111011 -
#3980000
0'
#3990000
b11000000 "
b11000000 5
1'
#3991000
b10111100 -
#4000000
0'
#4010000
b11000001 "
b11000001 5
1'
#4011000
b10111101 -
#4020000
0'
#4030000
b11000010 "
b11000010 5
1'
#4031000
b10111110 -
#4040000
0'
#4050000
b11000011 "
b11000011 5
1'
#4051000
b10111111 -
#4060000
0'
#4070000
b11000100 "
b11000100 5
1'
#4071000
b11000000 -
#4080000
0'
#4090000
b11000101 "
b11000101 5
1'
#4091000
b11000001 -
#4100000
0'
#4110000
b11000110 "
b11000110 5
1'
#4111000
b11000010 -
#4120000
0'
#4130000
b11000111 "
b11000111 5
1'
#4131000
b11000011 -
#4140000
0'
#4150000
b11001000 "
b11001000 5
1'
#4151000
b11000100 -
#4160000
0'
#4170000
b11001001 "
b11001001 5
1'
#4171000
b11000101 -
#4180000
0'
#4190000
b11001010 "
b11001010 5
1'
#4191000
b11000110 -
#4200000
0'
#4210000
b11001011 "
b11001011 5
1'
#4211000
b11000111 -
#4220000
0'
#4230000
b11001100 "
b11001100 5
1'
#4231000
b11001000 -
#4240000
0'
#4250000
b11001101 "
b11001101 5
1'
#4251000
b11001001 -
#4260000
0'
#4270000
b11001110 "
b11001110 5
1'
#4271000
b11001010 -
#4280000
0'
#4290000
b11001111 "
b11001111 5
1'
#4291000
b11001011 -
#4300000
0'
#4310000
b11010000 "
b11010000 5
1'
#4311000
b11001100 -
#4320000
0'
#4330000
b11010001 "
b11010001 5
1'
#4331000
b11001101 -
#4340000
0'
#4350000
b11010010 "
b11010010 5
1'
#4351000
b11001110 -
#4360000
0'
#4370000
b11010011 "
b11010011 5
1'
#4371000
b11001111 -
#4380000
0'
#4390000
b11010100 "
b11010100 5
1'
#4391000
b11010000 -
#4400000
0'
#4410000
b11010101 "
b11010101 5
1'
#4411000
b11010001 -
#4420000
0'
#4430000
b11010110 "
b11010110 5
1'
#4431000
b11010010 -
#4440000
0'
#4450000
b11010111 "
b11010111 5
1'
#4451000
b11010011 -
#4460000
0'
#4470000
b11011000 "
b11011000 5
1'
#4471000
b11010100 -
#4480000
0'
#4490000
b11011001 "
b11011001 5
1'
#4491000
b11010101 -
#4500000
0'
#4510000
b11011010 "
b11011010 5
1'
#4511000
b11010110 -
#4520000
0'
#4530000
b11011011 "
b11011011 5
1'
#4531000
b11010111 -
#4540000
0'
#4550000
b11011100 "
b11011100 5
1'
#4551000
b11011000 -
#4560000
0'
#4570000
b11011101 "
b11011101 5
1'
#4571000
b11011001 -
#4580000
0'
#4590000
b11011110 "
b11011110 5
1'
#4591000
b11011010 -
#4600000
0'
#4610000
b11011111 "
b11011111 5
1'
#4611000
b11011011 -
#4620000
0'
#4630000
b11100000 "
b11100000 5
1'
#4631000
b11011100 -
#4640000
0'
#4650000
b11100001 "
b11100001 5
1'
#4651000
b11011101 -
#4660000
0'
#4670000
b11100010 "
b11100010 5
1'
#4671000
b11011110 -
#4680000
0'
#4690000
b11100011 "
b11100011 5
1'
#4691000
b11011111 -
#4700000
0'
#4710000
b11100100 "
b11100100 5
1'
#4711000
b11100000 -
#4720000
0'
#4730000
b11100101 "
b11100101 5
1'
#4731000
b11100001 -
#4740000
0'
#4750000
b11100110 "
b11100110 5
1'
#4751000
b11100010 -
#4760000
0'
#4770000
b11100111 "
b11100111 5
1'
#4771000
b11100011 -
#4780000
0'
#4790000
b11101000 "
b11101000 5
1'
#4791000
b11100100 -
#4800000
0'
#4810000
b11101001 "
b11101001 5
1'
#4811000
b11100101 -
#4820000
0'
#4830000
b11101010 "
b11101010 5
1'
#4831000
b11100110 -
#4840000
0'
#4850000
b11101011 "
b11101011 5
1'
#4851000
b11100111 -
#4860000
0'
#4870000
b11101100 "
b11101100 5
1'
#4871000
b11101000 -
#4880000
0'
#4890000
b11101101 "
b11101101 5
1'
