src/reset_sync.v
`timescale 1ns/1ps

// Active-low reset conditioner: assertion is asynchronous; deassertion takes
// two CLK edges.  Downstream sequential logic uses reset_n_sync.
module reset_sync (
    input  wire clk,
    input  wire reset_n,
    output wire reset_n_sync
);
    reg [1:0] release_pipe;

    always @(posedge clk or negedge reset_n) begin
        if (!reset_n)
            release_pipe <= 2'b00;
        else
            release_pipe <= {release_pipe[0], 1'b1};
    end

    assign reset_n_sync = release_pipe[1];
endmodule

testbench/reset_sync_tb.v
`timescale 1ns/1ps

module reset_sync_tb;

    reg clk;
    reg reset_n;

    wire reset_n_sync;

    integer errors;

    reset_sync dut (
        .clk          (clk),
        .reset_n      (reset_n),
        .reset_n_sync (reset_n_sync)
    );

    always #10 clk = ~clk;


    task fail;
        input [8*100-1:0] message;
        begin
            errors = errors + 1;
            $display("FAIL: %0s", message);
        end
    endtask


    initial begin

        clk    = 1'b0;
        reset_n = 1'b0;
        errors = 0;

        $dumpfile("output/simulation_artifacts/reset_sync_tb.vcd");
        $dumpvars(0, reset_sync_tb);


        // ============================================================
        // TEST 1: RESET ASSERTION
        // ============================================================

        $display("");
        $display("TEST 1: Reset assertion");

        #1;

        if (reset_n_sync !== 1'b0)
            fail("reset_n_sync must be 0 while reset is asserted");


        // ============================================================
        // TEST 2: RESET REMAINS ASSERTED
        // ============================================================

        $display("");
        $display("TEST 2: Reset held low");

        repeat (3) begin
            @(posedge clk);
            #1;

            if (reset_n_sync !== 1'b0)
                fail("reset_n_sync must remain 0 while reset_n is low");
        end


        // ============================================================
        // TEST 3: FIRST CLOCK AFTER RESET RELEASE
        // ============================================================

        $display("");
        $display("TEST 3: First clock after reset release");

        reset_n = 1'b1;

        @(posedge clk);
        #1;

        if (reset_n_sync !== 1'b0)
            fail("reset_n_sync must remain 0 after first release clock");


        // ============================================================
        // TEST 4: SECOND CLOCK AFTER RESET RELEASE
        // ============================================================

        $display("");
        $display("TEST 4: Second clock after reset release");

        @(posedge clk);
        #1;

        if (reset_n_sync !== 1'b1)
            fail("reset_n_sync must become 1 after second release clock");


        // ============================================================
        // TEST 5: RESET SYNC REMAINS HIGH
        // ============================================================

        $display("");
        $display("TEST 5: Synchronized reset remains released");

        repeat (3) begin
            @(posedge clk);
            #1;

            if (reset_n_sync !== 1'b1)
                fail("reset_n_sync must remain 1 after reset release");
        end


        // ============================================================
        // TEST 6: ASYNCHRONOUS RESET RE-ASSERTION
        // ============================================================

        $display("");
        $display("TEST 6: Asynchronous reset re-assertion");

        reset_n = 1'b0;

        #1;

        if (reset_n_sync !== 1'b0)
            fail("reset_n_sync must clear immediately when reset_n goes low");


        // ============================================================
        // TEST 7: SECOND RELEASE SEQUENCE
        // ============================================================

        $display("");
        $display("TEST 7: Second reset release sequence");

        reset_n = 1'b1;

        @(posedge clk);
        #1;

        if (reset_n_sync !== 1'b0)
            fail("reset_n_sync must remain 0 after first clock of second release");

        @(posedge clk);
        #1;

        if (reset_n_sync !== 1'b1)
            fail("reset_n_sync must become 1 after second clock of second release");


        // ============================================================
        // FINAL RESULT
        // ============================================================

        $display("");

        if (errors == 0)
            $display("PASS: reset_sync unit verification");
        else
            $display(
                "FAIL: reset_sync unit verification: %0d checks failed",
                errors
            );

        $finish;

    end

endmodule

output/simulation_artifacts/reset_sync_tb.vcd
$date
	Mon Sep  7 21:49:01 2026
$end
$version
	Icarus Verilog
$end
$timescale
	1ps
$end
$scope module reset_sync_tb $end
$var wire 1 ! reset_n_sync $end
$var reg 1 " clk $end
$var reg 1 # reset_n $end
$var integer 32 $ errors [31:0] $end
$scope module dut $end
$var wire 1 " clk $end
$var wire 1 # reset_n $end
$var wire 1 ! reset_n_sync $end
$var reg 2 % release_pipe [1:0] $end
$upscope $end
$scope task fail $end
$var reg 800 & message [799:0] $end
$upscope $end
$upscope $end
$enddefinitions $end
$comment Show the parameter values. $end
$dumpall
$end
#0
$dumpvars
bx &
b0 %
b0 $
0#
0"
0!
$end
#10000
1"
#20000
0"
#30000
1"
#40000
0"
#50000
1"
#51000
1#
#60000
0"
#70000
b1 %
1"
#80000
0"
#90000
1!
b11 %
1"
#100000
0"
#110000
1"
#120000
0"
#130000
1"
#140000
0"
#150000
1"
#151000
0!
b0 %
0#
#152000
1#
#160000
0"
#170000
b1 %
1"
#180000
0"
#190000
1!
b11 %
1"
